Workbook
Name Slicer_Category: #N/A
Name Slicer_Channel: #N/A
Name Slicer_Months__Order_Date: #N/A
Name Slicer_Regions: #N/A
Name Slicer_Years__Order_Date: #N/A

Sheet Sales_Transactions
A1: Order_ID | B1: Order_Date | C1: Customer_ID | D1: Product_ID | E1: Store_ID | F1: Channel | G1: Quantity | H1: Unit_Price | I1: Discount | J1: Payment_Method
A2: ORD-10001 | B2: 46174 | C2: CUST-00070 | D2: PROD-0044 | E2: ST-008 | F2: Physical Store | G2: 1 | H2: 503.99 | I2: 0.02 | J2: Mobile Money
A3: ORD-10002 | B3: 46174 | C3: CUST-00041 | D3: PROD-0040 | E3: ST-003 | F3: Physical Store | G3: 3 | H3: 99 | I3: 0.1 | J3: Transfer
A4: ORD-10003 | B4: 45974 | C4: CUST-00686 | D4: PROD-0046 | E4: ST-011 | F4: Online | G4: 2 | H4: 79.79 | I4: 5% | J4: Transfer
A5: ORD-10004 | B5: 46104 | C5: CUST-00324 | D5: PROD-0060 | E5: ST-003 | F5: Online | G5: 2 | H5: 111.18 | I5: 0 | J5: Card
A6: ORD-10005 | B6: 46145 | C6: CUST-00219 | D6: PROD-0033 | E6: ST-009 | F6: Online | G6: 6 | H6: 2523.99 | I6: 0 | J6: Cash
A7: ORD-10006 | B7: 46059 | C7: CUST-00292 | D7: PROD-0011 | E7: ST-015 | F7: Physical Store | G7: 3 | H7: 1917.99 | I7: 0 | J7: mobile money
A8: ORD-10007 | B8: 46023 | C8: CUST-00680 | D8: PROD-0007 | E8: ST-005 | F8: Physical Store | G8: 1 | H8: 1799 | I8: 0 | J8: Mobile Money
A9: ORD-10008 | B9: 45949 | C9: CUST-00279 | D9: PROD-0019 | E9: ST-020 | F9: Online | G9: 4 | H9: 304.98 | I9: 0.02 | J9: Transfer
A10: ORD-10009 | B10: 46128 | C10: CUST-00501 | D10: PROD-0017 | E10: ST-002 | F10: Online | G10: 3 | H10: 1008.99 | I10: 0.05 | J10: Card
A11: ORD-10010 | B11: 45871 | D11: PROD-0050 | E11: ST-005 | F11: Physical Store | G11: 1 | H11: 115.43 | I11: 0.2 | J11: Mobile Money
A12: ORD-10011 | B12: 46231 | C12: CUST-00438 | D12: PROD-0036 | E12: ST-001 | F12: Online | G12: 1 | H12: 1234.97 | I12: 0 | J12: Mobile Money
A13: ORD-10012 | B13: 45888 | C13: CUST-00379 | D13: PROD-0038 | E13: ST-018 | F13: Online | G13: 2 | H13: 244.02 | I13: 0 | J13: Transfer
A14: ORD-10013 | B14: 46056 | C14: CUST-00041 | E14: ST-012 | F14: Online | G14: 3 | H14: 146,066 | I14: 0 | J14: Transfer
A15: ORD-10014 | B15: 46156 | C15: CUST-00417 | D15: PROD-0040 | E15: ST-005 | F15: Online | G15: 5 | H15: 101.97 | I15: 0 | J15: USSD
A16: ORD-10015 | B16: 45882 | C16: CUST-00184 | D16: PROD-0048 | E16: ST-011 | F16: Physical Store | G16: 4 | H16: 117.81 | I16: 0.02 | J16: Transfer
A17: ORD-10016 | B17: 45951 | C17: CUST-00719 | D17: PROD-0007 | E17: ST-013 | F17: Online | G17: 5 | H17: 1799 | I17: 0.02 | J17: Cash
A18: ORD-10017 | B18: 46105 | C18: CUST-00359 | D18: PROD-0020 | E18: ST-008 | F18: Online | G18: 1 | H18: 399 | I18: 0.02 | J18: USSD
A19: ORD-10018 | B19: 46038 | C19: CUST-00286 | D19: PROD-0056 | E19: ST-003 | F19: Physical Store | G19: 2 | H19: 157.41 | I19: 0.15 | J19: Mobile Money
A20: ORD-10019 | B20: 46039 | C20: CUST-00029 | D20: PROD-0008 | E20: ST-009 | F20: Online | G20: 3 | H20: 2367.97 | I20: 0.05 | J20: CARD
A21: ORD-10020 | B21: 45925 | C21: CUST-00611 | D21: PROD-0028 | E21: ST-012 | F21: Physical Store | G21: 2 | H21: 999 | I21: 0 | J21: USSD
A22: ORD-10021 | B22: 46165 | C22: CUST-00195 | D22: PROD-0017 | E22: ST-002 | F22: Physical Store | G22: 1 | H22: 969.03 | I22: 0.02 | J22: Transfer
A23: ORD-10022 | B23: 46090 | C23: CUST-00072 | D23: PROD-0043 | E23: ST-011 | F23: Physical Store | G23: 3 | H23: 307.97 | I23: 0 | J23: Transfer
A24: ORD-10023 | B24: 46129 | C24: CUST-00317 | D24: PROD-0043 | E24: ST-014 | F24: Physical Store | G24: 2 | H24: 304.98 | I24: 0.05 | J24: Mobile Money
A25: ORD-10024 | B25: 45935 | C25: CUST-00197 | D25: PROD-0027 | E25: ST-013 | F25: Online | G25: 3 | H25: 1357.03 | I25: 0.05 | J25: USSD
A26: ORD-10025 | B26: 46150 | C26: CUST-00001 | D26: PROD-0020 | E26: ST-010 | F26: Online | G26: 2 | H26: 410.97 | I26: 0.1 | J26: USSD
... A49: ORD-10048 | B49: 46029 | C49: CUST-00111 | D49: PROD-0038 | E49: ST-001 | F49: Physical Store | G49: 3 | H49: 253.98 | I49: 0.15 | J49: USSD
A50: ORD-10049 | B50: 45971 | C50: CUST-00078 | E50: ST-008 | F50: Online | G50: 3 | H50: 375779 | I50: 0.05 | J50: Mobile Money
A51: ORD-10050 | B51: 45931 | C51: CUST-00580 | D51: PROD-0051 | E51: ST-002 | F51: Physical Store | G51: 3 | H51: 86.33 | I51: 0.1 | J51: Card
A52: ORD-10051 | B52: 46129 | C52: CUST-00664 | D52: PROD-0022 | E52: ST-001 | F52: Physical Store | G52: 4 | H52: 1286.01 | I52: 0 | J52: USSD
A53: ORD-10052 | B53: 46055 | C53: CUST-00651 | D53: PROD-0058 | E53: ST-015 | F53: Online | G53: 2 | H53: 80.58 | I53: 0.05 | J53: Mobile Money
A54: ORD-10053 | B54: 46145 | C54: CUST-00794 | D54: PROD-0031 | E54: ST-015 | F54: Physical Store | G54: 4 | H54: 1599 | I54: 0.05 | J54: Transfer
A55: ORD-10054 | B55: 45995 | C55: CUST-00089 | D55: PROD-0018 | E55: ST-015 | F55: Online | G55: 4 | H55: 874.47 | I55: 0.15 | J55: Transfer
A56: ORD-10055 | B56: 45884 | C56: CUST-00507 | D56: PROD-0055 | E56: ST-011 | F56: Online | G56: 2 | H56: 97.02 | I56: 0.1 | J56: Transfer
A57: ORD-10056 | B57: 46044 | C57: CUST-00287 | D57: PROD-0057 | E57: ST-020 | F57: Physical Store | G57: 3 | H57: 127.71 | I57: 0.02 | J57: Card
A58: ORD-10057 | B58: 45993 | C58: CUST-00738 | D58: PROD-0027 | E58: ST-016 | F58: Online | G58: 3 | H58: 1399 | I58: 0.2 | J58: USSD
A59: ORD-10058 | B59: 45878 | C59: CUST-00096 | D59: PROD-0019 | E59: ST-008 | F59: Physical Store | G59: 3 | H59: 301.99 | I59: 0.05 | J59: Mobile Money
A60: ORD-10059 | B60: 46058 | C60: CUST-00485 | D60: PROD-0036 | E60: ST-017 | F60: Physical Store | G60: 2 | H60: 1187.01 | I60: 0.1 | J60: Transfer
A61: ORD-10060 | B61: 46229 | C61: CUST-00465 | D61: PROD-0018 | E61: ST-010 | F61: Physical Store | G61: 1 | H61: 832.02 | I61: 0.02 | J61: Transfer
A62: ORD-10061 | B62: 45931 | C62: CUST-00761 | D62: PROD-0035 | E62: ST-006 | F62: Online | G62: 1 | H62: 1018.98 | I62: 0.2 | J62: Transfer
... A70: ORD-10069 | B70: 46171 | C70: CUST-00440 | D70: PROD-0020 | E70: ST-019 | F70: Online | G70: 3 | H70: 406.98 | I70: 0 | J70: Cash
A71: ORD-10070 | B71: 46190 | C71: CUST-00217 | D71: PROD-0017 | F71: Online | G71: 2 | H71: 969.03 | I71: 0 | J71: Cash
A72: ORD-10071 | B72: 45871 | C72: CUST-00419 | D72: PROD-0029 | E72: ST-020 | F72: Physical Store | G72: 2 | H72: 1528.98 | I72: 0.02 | J72: Transfer
A73: ORD-10072 | B73: 46231 | C73: CUST-00290 | D73: PROD-0045 | E73: ST-015 | F73: Online | G73: 3 | H73: 395.01 | I73: 0.05 | J73: Mobile Money
A74: ORD-10073 | B74: 46208 | C74: CUST-00203 | D74: PROD-0028 | E74: ST-004 | F74: Online | G74: 3 | H74: 1028.97 | I74: 0.05 | J74: Cash
A75: ORD-10074 | B75: 45906 | C75: CUST-00062 | D75: PROD-0011 | E75: ST-010 | F75: Physical Store | G75: 2 | H75: 1861.02 | I75: 0.2 | J75: Transfer
A76: ORD-10075 | B76: 46228 | C76: CUST-00413 | D76: PROD-0018 | E76: ST-017 | F76: Physical Store | G76: 2 | H76: 865.98 | I76: 0 | J76: USSD
A77: ORD-10076 | B77: 46035 | C77: CUST-00619 | D77: PROD-0017 | E77: ST-001 | F77: Online | G77: 1 | H77: 999 | I77: 0 | J77: Transfer
A78: ORD-10077 | B78: 46165 | C78: CUST-00042 | D78: PROD-0049 | E78: ST-006 | F78: Physical Store | G78: 3 | H78: 68.31 | I78: 0.2 | J78: Transfer
A79: ORD-10078 | B79: 45962 | C79: CUST-00600 | D79: PROD-0028 | E79: ST-016 | F79: ONLINE | G79: 2 | H79: 999 | I79: 0.15 | J79: Transfer
A80: ORD-10079 | B80: 46034 | C80: CUST-00687 | D80: PROD-0007 | E80: ST-006 | F80: Physical Store | G80: 2 | H80: 1781.01 | I80: 0.2 | J80: Transfer
A81: ORD-10080 | B81: 46209 | C81: CUST-00411 | D81: PROD-0053 | E81: ST-018 | F81: Online | G81: 2 | H81: 71.07 | I81: 0.1 | J81: Transfer
A82: ORD-10081 | B82: 46035 | C82: CUST-00119 | D82: PROD-0050 | E82: ST-013 | F82: Online | G82: 3 | H82: 122.57 | I82: 0.2 | J82: USSD
A83: ORD-10082 | B83: 45897 | C83: CUST-00193 | D83: PROD-0034 | E83: ST-012 | F83: Physical Store | G83: 3 | H83: 678.03 | I83: 0 | J83: cash
... A108: ORD-10107 | B108: 46191 | C108: CUST-00100 | D108: PROD-0058 | E108: ST-002 | F108: Physical Store | G108: 4 | H108: 77.42 | I108: 0 | J108: Mobile Money
A109: ORD-10108 | B109: 02/03/2026 | C109: CUST-00750 | D109: PROD-0009 | E109: ST-003 | F109: Physical Store | G109: 2 | H109: 1979.01 | I109: 0.15 | J109: Cash
A110: ORD-10109 | B110: 45972 | C110: CUST-00136 | D110: PROD-0051 | E110: ST-018 | F110: Physical Store | G110: 3 | H110: 87.22 | I110: 0.05 | J110: Cash
A111: ORD-10110 | B111: 46001 | C111: CUST-00494 | D111: PROD-0052 | E111: ST-010 | F111: Physical Store | G111: 4 | H111: 38.22 | I111: 0.2 | J111: Card
A112: ORD-10111 | B112: 45942 | C112: CUST-00773 | D112: PROD-0015 | E112: ST-013 | F112: Physical Store | G112: 1 | H112: 532.53 | I112: 0.15 | J112: Card
A113: ORD-10112 | B113: 14-12-2025 | C113: CUST-00550 | D113: PROD-0008 | E113: ST-015 | F113: Physical Store | G113: 3 | H113: 2299 | I113: 0.05 | J113: Mobile Money
A114: ORD-10113 | B114: 46065 | C114: CUST-00654 | D114: PROD-0024 | E114: ST-004 | F114: Online | G114: 2 | H114: 1440.97 | I114: 0.1 | J114: Mobile Money
A115: ORD-10114 | B115: 45983 | C115: CUST-00664 | D115: PROD-0005 | E115: ST-015 | F115: Physical Store | G115: 3 | H115: 1543.97 | I115: 0 | J115: Cash
A116: ORD-10115 | B116: 45893 | C116: CUST-00039 | D116: PROD-0020 | E116: ST-016 | F116: Online | G116: 1 | H116: 391.02 | I116: 0 | J116: USSD
A117: ORD-10116 | B117: 46102 | C117: CUST-00380 | D117: PROD-0043 | E117: ST-018 | F117: Physical Store | G117: 3 | H117: 301.99 | I117: 0 | J117: USSD
A118: ORD-10117 | B118: 46205 | C118: CUST-00102 | D118: PROD-0054 | E118: ST-016 | F118: Physical Store | G118: 6 | H118: 53.9 | I118: 0.05 | J118: Card
A119: ORD-10118 | B119: 46223 | C119: CUST-00380 | D119: PROD-0014 | E119: ST-015 | F119: Physical Store | G119: 6 | H119: 749 | I119: 0.1 | J119: Card
A120: ORD-10119 | B120: 46221 | C120: CUST-00377 | D120: PROD-0035 | E120: ST-012 | F120: Online | G120: 2 | H120: 1018.98 | I120: 0.02 | J120: Card
A121: ORD-10120 | B121: 46102 | C121: CUST-00094 | D121: PROD-0043 | E121: ST-007 | F121: Online | G121: 1 | H121: 301.99 | I121: 0.1 | J121: Cash
A122: ORD-10121 | B122: 45934 | C122: CUST-00579 | D122: PROD-0014 | E122: ST-003 | F122: Online | G122: 3 | H122: 771.47 | I122: 0.02 | J122: Transfer
A123: ORD-10122 | B123: 45945 | C123: CUST-00611 | D123: PROD-0001 | E123: ST-009 | F123: Online | G123: 8 | H123: 699 | I123: 0.05 | J123: Cash
A124: ORD-10123 | B124: 45926 | C124: CUST-00677 | D124: PROD-0056 | E124: ST-001 | F124: Online | G124: 1 | H124: 154.23 | I124: 0.02 | J124: Mobile Money
A125: ORD-10124 | B125: 46035 | C125: CUST-00017 | D125: PROD-0012 | E125: ST-009 | F125: Online | G125: 1 | H125: 2119.99 | I125: 0.35 | J125: Mobile Money
... A151: ORD-10150 | B151: 45915 | C151: CUST-00448 | D151: PROD-0055 | E151: ST-004 | F151: Online | G151: 2 | H151: 97.02 | I151: 0.15 | J151: Mobile Money
A152: ORD-10151 | B152: 09/10/2025 | C152: CUST-00406 | D152: PROD-0056 | E152: ST-010 | F152: Physical Store | G152: 1 | H152: 163.77 | I152: 0 | J152: Card
A153: ORD-10152 | B153: 46131 | C153: CUST-00649 | D153: PROD-0008 | E153: ST-017 | F153: Online | G153: 5 | H153: 2344.98 | I153: 0.1 | J153: Transfer
A154: ORD-10153 | B154: 46200 | C154: CUST-00152 | D154: PROD-0016 | E154: ST-004 | F154: Online | G154: 2 | H154: 705.99 | I154: 0 | J154: Mobile Money
A155: ORD-10154 | B155: 45948 | C155: CUST-00779 | D155: PROD-0049 | E155: ST-003 | F155: Online | G155: 6 | H155: 67.62 | I155: 0.2 | J155: USSD
A156: ORD-10155 | B156: 46158 | C156: CUST-00779 | D156: PROD-0038 | E156: ST-015 | F156: Physical Store | G156: 5 | H156: 256.47 | I156: 0.1 | J156: Cash
A157: ORD-10156 | B157: 46095 | C157: CUST-00070 | D157: PROD-0031 | E157: ST-015 | F157: Physical Store | G157: 4 | H157: 1567.02 | I157: -0.05 | J157: transfer
A158: ORD-10157 | B158: 46129 | C158: CUST-00076 | D158: PROD-0020 | E158: ST-015 | F158: Physical Store | G158: 1 | H158: 399 | I158: 0.1 | J158: Transfer
A159: ORD-10158 | B159: 45909 | C159: CUST-00661 | D159: PROD-0056 | E159: ST-003 | F159: Physical Store | G159: 2 | H159: 162.18 | I159: 0 | J159: USSD
A160: ORD-10159 | B160: 46162 | C160: CUST-00668 | D160: PROD-0013 | E160: ST-011 | F160: Physical Store | G160: 3 | H160: 241.53 | I160: 0 | J160: USSD
A161: ORD-10160 | B161: 45922 | C161: CUST-00352 | D161: PROD-0046 | E161: ST-003 | F161: Online | G161: 1 | H161: 79 | I161: 0.2 | J161: USSD
A162: ORD-10161 | B162: 46138 | C162: CUST-00536 | D162: PROD-0040 | E162: ST-006 | F162: Physical Store | G162: 2 | H162: 96.03 | I162: 0.05 | J162: USSD
A163: ORD-10162 | B163: 46079 | C163: CUST-00794 | D163: PROD-0022 | E163: ST-020 | F163: Online | G163: 4 | H163: 1299 | I163: 0.1 | J163: Card
A164: ORD-10163 | B164: 46038 | C164: CUST-00097 | D164: PROD-0036 | E164: ST-013 | F164: Physical Store | G164: 2 | H164: 1187.01 | I164: 0 | J164: Transfer
... A214: ORD-10213 | B214: 45891 | C214: CUST-00030 | D214: PROD-0006 | E214: ST-002 | F214: Physical Store | G214: 3 | H214: 1286.01 | I214: 0.15 | J214: Mobile Money
A215: ORD-10214 | B215: 46197 | C215: CUST-00032 | D215: PROD-0032 | E215: ST-018 | F215: Physical Store | G215: 3 | H215: 2220.99 | J215: USSD
A216: ORD-10215 | B216: 45995 | C216: CUST-00702 | D216: PROD-0026 | E216: ST-010 | F216: Physical Store | G216: 1 | H216: 1648.03 | I216: 0 | J216: Cash
A217: ORD-10216 | B217: 46095 | C217: CUST-00426 | D217: PROD-0031 | E217: ST-015 | F217: Online | G217: 2 | H217: 1630.98 | I217: 0 | J217: Transfer
A218: ORD-10217 | B218: 46033 | C218: CUST-00752 | D218: PROD-0056 | E218: ST-012 | F218: Physical Store | G218: 1 | H218: 154.23 | I218: 0.1 | J218: Mobile Money
A219: ORD-10218 | B219: 46157 | C219: CUST-00109 | D219: PROD-0021 | E219: ST-008 | F219: Physical Store | G219: 1 | H219: 453.49 | I219: 0.2 | J219: Cash
A220: ORD-10219 | B220: 45942 | D220: PROD-0004 | E220: ST-010 | F220: Physical Store | G220: 5 | H220: 1454.03 | I220: 0.15 | J220: Cash
A221: ORD-10220 | B221: 45951 | C221: CUST-00336 | D221: PROD-0060 | E221: ST-019 | F221: Physical Store | G221: 1 | H221: 110.09 | I221: 0 | J221: USSD
A222: ORD-10221 | B222: 46133 | C222: CUST-00479 | D222: PROD-0032 | E222: ST-010 | F222: Physical Store | G222: 1 | H222: 2177.01 | I222: 0.15 | J222: Mobile Money
A223: ORD-10222 | B223: 46104 | C223: CUST-00247 | D223: PROD-0014 | E223: ST-019 | F223: Physical Store | G223: 1 | H223: 763.98 | I223: 0.05 | J223: USSD
A224: ORD-10223 | B224: 46175 | C224: CUST-00670 | D224: PROD-0044 | E224: ST-016 | F224: Physical Store | G224: 3 | H224: 484.03 | I224: 0 | J224: USSD
A225: ORD-10224 | B225: 45938 | C225: CUST-00271 | D225: PROD-0047 | E225: ST-012 | F225: Physical Store | G225: 2 | H225: 146.02 | I225: 0.15 | J225: Card
A226: ORD-10225 | B226: 46161 | C226: CUST-00576 | D226: PROD-0013 | E226: ST-012 | F226: Physical Store | G226: 1 | H226: 246.51 | I226: 0.2 | J226: MOBILE MONEY
A227: ORD-10226 | B227: 46013 | C227: CUST-00639 | D227: PROD-0044 | E227: ST-020 | F227: Online | G227: 1 | H227: 499 | I227: 0 | J227: USSD
...

Sheet Cleaned_S_T
A1: Order_ID | B1: Order_Date | C1: Customer_ID | D1: Customer Segement | E1: Product_ID | F1: Category | G1: Regions | H1: Store_ID | I1: Channel | J1: Quantity | K1: Unit_Price | L1: Discount | M1: Payment_Method | N1: Cost Price | O1: Revenue | P1: Profit | Q1: Profit Margin | R1: COGS
A2: ORD-10001 | B2: 46028 | C2: CUST-00070 | D2: =VLOOKUP(C2,Customers!A:E,5,FALSE) -> Affluent | E2: PROD-0044 | F2: =VLOOKUP(Table1[[#This Row],[Product_ID]],Products!A:D,4,FALSE) -> Audio | G2: =VLOOKUP(H2,Stores!A:E,5,FALSE) -> Asia | H2: ST-008 | I2: Physical Store | J2: 1 | K2: 503.99 | L2: 0.02 | M2: Transfer | N2: 354.29 | O2: =Table1[[#This Row],[Unit_Price]]*Table1[[#This Row],[Quantity]] -> 503.99 | P2: =Table1[[#This Row],[Revenue]]-Table1[[#This Row],[COGS]] -> 149.7 | Q2: =Table1[[#This Row],[Profit]]/Table1[[#This Row],[Revenue]] -> 0.2970297 | R2: =Table1[[#This Row],[Cost Price]]*Table1[[#This Row],[Quantity]] -> 354.29
A3: ORD-10002 | B3: 46028 | C3: CUST-00041 | D3: =VLOOKUP(C3,Customers!A:E,5,FALSE) -> Mass Market | E3: PROD-0040 | F3: =VLOOKUP(Table1[[#This Row],[Product_ID]],Products!A:D,4,FALSE) -> Audio | G3: =VLOOKUP(H3,Stores!A:E,5,FALSE) -> Africa | H3: ST-003 | I3: Physical Store | J3: 3 | K3: 99 | L3: 0.1 | M3: Transfer | N3: 71.28 | O3: =Table1[[#This Row],[Unit_Price]]*Table1[[#This Row],[Quantity]] -> 297 | P3: =Table1[[#This Row],[Revenue]]-Table1[[#This Row],[COGS]] -> 83.16 | Q3: =Table1[[#This Row],[Profit]]/Table1[[#This Row],[Revenue]] -> 0.28 | R3: =Table1[[#This Row],[Cost Price]]*Table1[[#This Row],[Quantity]] -> 213.84
A4: ORD-10003 | B4: 45974 | C4: CUST-00686 | D4: =VLOOKUP(C4,Customers!A:E,5,FALSE) -> Mass Affluent | E4: PROD-0046 | F4: =VLOOKUP(Table1[[#This Row],[Product_ID]],Products!A:D,4,FALSE) -> Audio | G4: =VLOOKUP(H4,Stores!A:E,5,FALSE) -> Europe | H4: ST-011 | I4: Online | J4: 2 | K4: 79.79 | L4: 0.05 | M4: Transfer | N4: 57.67 | O4: =Table1[[#This Row],[Unit_Price]]*Table1[[#This Row],[Quantity]] -> 159.58 | P4: =Table1[[#This Row],[Revenue]]-Table1[[#This Row],[COGS]] -> 44.24 | Q4: =Table1[[#This Row],[Profit]]/Table1[[#This Row],[Revenue]] -> 0.27722772 | R4: =Table1[[#This Row],[Cost Price]]*Table1[[#This Row],[Quantity]] -> 115.34
A5: ORD-10004 | B5: 46104 | C5: CUST-00324 | D5: =VLOOKUP(C5,Customers!A:E,5,FALSE) -> Affluent | E5: PROD-0060 | F5: =VLOOKUP(Table1[[#This Row],[Product_ID]],Products!A:D,4,FALSE) -> Accessories | G5: =VLOOKUP(H5,Stores!A:E,5,FALSE) -> Africa | H5: ST-003 | I5: Online | J5: 2 | K5: 111.18 | L5: 0 | M5: Card | N5: 78.48 | O5: =Table1[[#This Row],[Unit_Price]]*Table1[[#This Row],[Quantity]] -> 222.36 | P5: =Table1[[#This Row],[Revenue]]-Table1[[#This Row],[COGS]] -> 65.4 | Q5: =Table1[[#This Row],[Profit]]/Table1[[#This Row],[Revenue]] -> 0.29411765 | R5: =Table1[[#This Row],[Cost Price]]*Table1[[#This Row],[Quantity]] -> 156.96
A6: ORD-10005 | B6: 46086 | C6: CUST-00219 | D6: =VLOOKUP(C6,Customers!A:E,5,FALSE) -> Mass Market | E6: PROD-0033 | F6: =VLOOKUP(Table1[[#This Row],[Product_ID]],Products!A:D,4,FALSE) -> Laptops | G6: =VLOOKUP(H6,Stores!A:E,5,FALSE) -> Asia | H6: ST-009 | I6: Online | J6: 6 | K6: 2523.99 | L6: 0 | M6: Cash | N6: 1599.36 | O6: =Table1[[#This Row],[Unit_Price]]*Table1[[#This Row],[Quantity]] -> 15143.94 | P6: =Table1[[#This Row],[Revenue]]-Table1[[#This Row],[COGS]] -> 5547.78 | Q6: =Table1[[#This Row],[Profit]]/Table1[[#This Row],[Revenue]] -> 0.36633663 | R6: =Table1[[#This Row],[Cost Price]]*Table1[[#This Row],[Quantity]] -> 9596.16
A7: ORD-10006 | B7: 46175 | C7: CUST-00292 | D7: =VLOOKUP(C7,Customers!A:E,5,FALSE) -> Mass Market | E7: PROD-0011 | F7: =VLOOKUP(Table1[[#This Row],[Product_ID]],Products!A:D,4,FALSE) -> Televisions | G7: =VLOOKUP(H7,Stores!A:E,5,FALSE) -> North America | H7: ST-015 | I7: Physical Store | J7: 3 | K7: 1917.99 | L7: 0 | M7: Transfer | N7: 1177.38 | O7: =Table1[[#This Row],[Unit_Price]]*Table1[[#This Row],[Quantity]] -> 5753.97 | P7: =Table1[[#This Row],[Revenue]]-Table1[[#This Row],[COGS]] -> 2221.83 | Q7: =Table1[[#This Row],[Profit]]/Table1[[#This Row],[Revenue]] -> 0.38613861 | R7: =Table1[[#This Row],[Cost Price]]*Table1[[#This Row],[Quantity]] -> 3532.14
A8: ORD-10007 | B8: 46023 | C8: CUST-00680 | D8: =VLOOKUP(C8,Customers!A:E,5,FALSE) -> Mass Market | E8: PROD-0007 | F8: =VLOOKUP(Table1[[#This Row],[Product_ID]],Products!A:D,4,FALSE) -> Televisions | G8: =VLOOKUP(H8,Stores!A:E,5,FALSE) -> Africa | H8: ST-005 | I8: Physical Store | J8: 1 | K8: 1799 | L8: 0 | M8: Transfer | N8: 1097.39 | O8: =Table1[[#This Row],[Unit_Price]]*Table1[[#This Row],[Quantity]] -> 1799 | P8: =Table1[[#This Row],[Revenue]]-Table1[[#This Row],[COGS]] -> 701.61 | Q8: =Table1[[#This Row],[Profit]]/Table1[[#This Row],[Revenue]] -> 0.39 | R8: =Table1[[#This Row],[Cost Price]]*Table1[[#This Row],[Quantity]] -> 1097.39
A9: ORD-10008 | B9: 45949 | C9: CUST-00279 | D9: =VLOOKUP(C9,Customers!A:E,5,FALSE) -> Mass Affluent | E9: PROD-0019 | F9: =VLOOKUP(Table1[[#This Row],[Product_ID]],Products!A:D,4,FALSE) -> Smartphones | G9: =VLOOKUP(H9,Stores!A:E,5,FALSE) -> oceania | H9: ST-020 | I9: Online | J9: 4 | K9: 304.98 | L9: 0.02 | M9: Transfer | N9: 194.35 | O9: =Table1[[#This Row],[Unit_Price]]*Table1[[#This Row],[Quantity]] -> 1219.92 | P9: =Table1[[#This Row],[Revenue]]-Table1[[#This Row],[COGS]] -> 442.52 | Q9: =Table1[[#This Row],[Profit]]/Table1[[#This Row],[Revenue]] -> 0.3627451 | R9: =Table1[[#This Row],[Cost Price]]*Table1[[#This Row],[Quantity]] -> 777.4
A10: ORD-10009 | B10: 46128 | C10: CUST-00501 | D10: =VLOOKUP(C10,Customers!A:E,5,FALSE) -> Mass Market | E10: PROD-0017 | F10: =VLOOKUP(Table1[[#This Row],[Product_ID]],Products!A:D,4,FALSE) -> Smartphones | G10: =VLOOKUP(H10,Stores!A:E,5,FALSE) -> Africa | H10: ST-002 | I10: Online | J10: 3 | K10: 1008.99 | L10: 0.05 | M10: Card | N10: 609.39 | O10: =Table1[[#This Row],[Unit_Price]]*Table1[[#This Row],[Quantity]] -> 3026.97 | P10: =Table1[[#This Row],[Revenue]]-Table1[[#This Row],[COGS]] -> 1198.8 | Q10: =Table1[[#This Row],[Profit]]/Table1[[#This Row],[Revenue]] -> 0.3960396 | R10: =Table1[[#This Row],[Cost Price]]*Table1[[#This Row],[Quantity]] -> 1828.17
A11: ORD-10010 | B11: 45696 | C11: Unknown -00001 | D11: Unknown -00001 | E11: PROD-0050 | F11: =VLOOKUP(Table1[[#This Row],[Product_ID]],Products!A:D,4,FALSE) -> Accessories | G11: =VLOOKUP(H11,Stores!A:E,5,FALSE) -> Africa | H11: ST-005 | I11: Physical Store | J11: 1 | K11: 115.43 | L11: 0.2 | M11: Transfer | N11: 85.68 | O11: =Table1[[#This Row],[Unit_Price]]*Table1[[#This Row],[Quantity]] -> 115.43 | P11: =Table1[[#This Row],[Revenue]]-Table1[[#This Row],[COGS]] -> 29.75 | Q11: =Table1[[#This Row],[Profit]]/Table1[[#This Row],[Revenue]] -> 0.25773196 | R11: =Table1[[#This Row],[Cost Price]]*Table1[[#This Row],[Quantity]] -> 85.68
A12: ORD-10011 | B12: 46231 | C12: CUST-00438 | D12: =VLOOKUP(C12,Customers!A:E,5,FALSE) -> Mass Market | E12: PROD-0036 | F12: =VLOOKUP(Table1[[#This Row],[Product_ID]],Products!A:D,4,FALSE) -> Laptops | G12: =VLOOKUP(H12,Stores!A:E,5,FALSE) -> Africa | H12: ST-001 | I12: Online | J12: 1 | K12: 1234.97 | L12: 0 | M12: Transfer | N12: 875.27 | O12: =Table1[[#This Row],[Unit_Price]]*Table1[[#This Row],[Quantity]] -> 1234.97 | P12: =Table1[[#This Row],[Revenue]]-Table1[[#This Row],[COGS]] -> 359.7 | Q12: =Table1[[#This Row],[Profit]]/Table1[[#This Row],[Revenue]] -> 0.29126214 | R12: =Table1[[#This Row],[Cost Price]]*Table1[[#This Row],[Quantity]] -> 875.27
A13: ORD-10012 | B13: 45888 | C13: CUST-00379 | D13: =VLOOKUP(C13,Customers!A:E,5,FALSE) -> Mass Market | E13: PROD-0038 | F13: =VLOOKUP(Table1[[#This Row],[Product_ID]],Products!A:D,4,FALSE) -> Audio | G13: =VLOOKUP(H13,Stores!A:E,5,FALSE) -> South America | H13: ST-018 | I13: Online | J13: 2 | K13: 244.02 | L13: 0 | M13: Transfer | N13: 171.81 | O13: =Table1[[#This Row],[Unit_Price]]*Table1[[#This Row],[Quantity]] -> 488.04 | P13: =Table1[[#This Row],[Revenue]]-Table1[[#This Row],[COGS]] -> 144.42 | Q13: =Table1[[#This Row],[Profit]]/Table1[[#This Row],[Revenue]] -> 0.29591837 | R13: =Table1[[#This Row],[Cost Price]]*Table1[[#This Row],[Quantity]] -> 343.62
A14: ORD-10013 | B14: 46083 | C14: CUST-00041 | D14: =VLOOKUP(C14,Customers!A:E,5,FALSE) -> Mass Market | E14: Unknown- 001 | F14: =VLOOKUP(Table1[[#This Row],[Product_ID]],Products!A:D,4,FALSE) -> #N/A | G14: =VLOOKUP(H14,Stores!A:E,5,FALSE) -> Europe | H14: ST-012 | I14: Online | J14: 3 | K14: 146066 | L14: 0 | M14: Transfer | N14: 0 | O14: 0 | P14: =Table1[[#This Row],[Revenue]]-Table1[[#This Row],[COGS]] -> 0 | Q14: 0 | R14: =Table1[[#This Row],[Cost Price]]*Table1[[#This Row],[Quantity]] -> 0
A15: ORD-10014 | B15: 46156 | C15: CUST-00417 | D15: =VLOOKUP(C15,Customers!A:E,5,FALSE) -> Mass Market | E15: PROD-0040 | F15: =VLOOKUP(Table1[[#This Row],[Product_ID]],Products!A:D,4,FALSE) -> Audio | G15: =VLOOKUP(H15,Stores!A:E,5,FALSE) -> Africa | H15: ST-005 | I15: Online | J15: 5 | K15: 101.97 | L15: 0 | M15: Transfer | N15: 71.28 | O15: =Table1[[#This Row],[Unit_Price]]*Table1[[#This Row],[Quantity]] -> 509.85 | P15: =Table1[[#This Row],[Revenue]]-Table1[[#This Row],[COGS]] -> 153.45 | Q15: =Table1[[#This Row],[Profit]]/Table1[[#This Row],[Revenue]] -> 0.30097087 | R15: =Table1[[#This Row],[Cost Price]]*Table1[[#This Row],[Quantity]] -> 356.4
A16: ORD-10015 | B16: 45882 | C16: CUST-00184 | D16: =VLOOKUP(C16,Customers!A:E,5,FALSE) -> Mass Market | E16: PROD-0048 | F16: =VLOOKUP(Table1[[#This Row],[Product_ID]],Products!A:D,4,FALSE) -> Audio | G16: =VLOOKUP(H16,Stores!A:E,5,FALSE) -> Europe | H16: ST-011 | I16: Physical Store | J16: 4 | K16: 117.81 | L16: 0.02 | M16: Transfer | N16: 82.11 | O16: =Table1[[#This Row],[Unit_Price]]*Table1[[#This Row],[Quantity]] -> 471.24 | P16: =Table1[[#This Row],[Revenue]]-Table1[[#This Row],[COGS]] -> 142.8 | Q16: =Table1[[#This Row],[Profit]]/Table1[[#This Row],[Revenue]] -> 0.3030303 | R16: =Table1[[#This Row],[Cost Price]]*Table1[[#This Row],[Quantity]] -> 328.44
A17: ORD-10016 | B17: 45951 | C17: CUST-00719 | D17: =VLOOKUP(C17,Customers!A:E,5,FALSE) -> Mass Market | E17: PROD-0007 | F17: =VLOOKUP(Table1[[#This Row],[Product_ID]],Products!A:D,4,FALSE) -> Televisions | G17: =VLOOKUP(H17,Stores!A:E,5,FALSE) -> EUROPE | H17: ST-013 | I17: Online | J17: 5 | K17: 1799 | L17: 0.02 | M17: Cash | N17: 1097.39 | O17: =Table1[[#This Row],[Unit_Price]]*Table1[[#This Row],[Quantity]] -> 8995 | P17: =Table1[[#This Row],[Revenue]]-Table1[[#This Row],[COGS]] -> 3508.05 | Q17: =Table1[[#This Row],[Profit]]/Table1[[#This Row],[Revenue]] -> 0.39 | R17: =Table1[[#This Row],[Cost Price]]*Table1[[#This Row],[Quantity]] -> 5486.95
A18: ORD-10017 | B18: 46105 | C18: CUST-00359 | D18: =VLOOKUP(C18,Customers!A:E,5,FALSE) -> Mass Affluent | E18: PROD-0020 | F18: =VLOOKUP(Table1[[#This Row],[Product_ID]],Products!A:D,4,FALSE) -> Smartphones | G18: =VLOOKUP(H18,Stores!A:E,5,FALSE) -> Asia | H18: ST-008 | I18: Online | J18: 1 | K18: 399 | L18: 0.02 | M18: Transfer | N18: 287.28 | O18: =Table1[[#This Row],[Unit_Price]]*Table1[[#This Row],[Quantity]] -> 399 | P18: =Table1[[#This Row],[Revenue]]-Table1[[#This Row],[COGS]] -> 111.72 | Q18: =Table1[[#This Row],[Profit]]/Table1[[#This Row],[Revenue]] -> 0.28 | R18: =Table1[[#This Row],[Cost Price]]*Table1[[#This Row],[Quantity]] -> 287.28
A19: ORD-10018 | B19: 46038 | C19: CUST-00286 | D19: =VLOOKUP(C19,Customers!A:E,5,FALSE) -> Affluent | E19: PROD-0056 | F19: =VLOOKUP(Table1[[#This Row],[Product_ID]],Products!A:D,4,FALSE) -> Accessories | G19: =VLOOKUP(H19,Stores!A:E,5,FALSE) -> Africa | H19: ST-003 | I19: Physical Store | J19: 2 | K19: 157.41 | L19: 0.15 | M19: Transfer | N19: 116.07 | O19: =Table1[[#This Row],[Unit_Price]]*Table1[[#This Row],[Quantity]] -> 314.82 | P19: =Table1[[#This Row],[Revenue]]-Table1[[#This Row],[COGS]] -> 82.68 | Q19: =Table1[[#This Row],[Profit]]/Table1[[#This Row],[Revenue]] -> 0.26262626 | R19: =Table1[[#This Row],[Cost Price]]*Table1[[#This Row],[Quantity]] -> 232.14
A20: ORD-10019 | B20: 46039 | C20: CUST-00029 | D20: =VLOOKUP(C20,Customers!A:E,5,FALSE) -> Mass Market | E20: PROD-0008 | F20: =VLOOKUP(Table1[[#This Row],[Product_ID]],Products!A:D,4,FALSE) -> Televisions | G20: =VLOOKUP(H20,Stores!A:E,5,FALSE) -> Asia | H20: ST-009 | I20: Online | J20: 3 | K20: 2367.97 | L20: 0.05 | M20: Card | N20: 1586.31 | O20: =Table1[[#This Row],[Unit_Price]]*Table1[[#This Row],[Quantity]] -> 7103.91 | P20: =Table1[[#This Row],[Revenue]]-Table1[[#This Row],[COGS]] -> 2344.98 | Q20: =Table1[[#This Row],[Profit]]/Table1[[#This Row],[Revenue]] -> 0.33009709 | R20: =Table1[[#This Row],[Cost Price]]*Table1[[#This Row],[Quantity]] -> 4758.93
A21: ORD-10020 | B21: 45925 | C21: CUST-00611 | D21: =VLOOKUP(C21,Customers!A:E,5,FALSE) -> Mass Market | E21: PROD-0028 | F21: =VLOOKUP(Table1[[#This Row],[Product_ID]],Products!A:D,4,FALSE) -> Laptops | G21: =VLOOKUP(H21,Stores!A:E,5,FALSE) -> Europe | H21: ST-012 | I21: Physical Store | J21: 2 | K21: 999 | L21: 0 | M21: Transfer | N21: 689.31 | O21: =Table1[[#This Row],[Unit_Price]]*Table1[[#This Row],[Quantity]] -> 1998 | P21: =Table1[[#This Row],[Revenue]]-Table1[[#This Row],[COGS]] -> 619.38 | Q21: =Table1[[#This Row],[Profit]]/Table1[[#This Row],[Revenue]] -> 0.31 | R21: =Table1[[#This Row],[Cost Price]]*Table1[[#This Row],[Quantity]] -> 1378.62
A22: ORD-10021 | B22: 46165 | C22: CUST-00195 | D22: =VLOOKUP(C22,Customers!A:E,5,FALSE) -> Mass Affluent | E22: PROD-0017 | F22: =VLOOKUP(Table1[[#This Row],[Product_ID]],Products!A:D,4,FALSE) -> Smartphones | G22: =VLOOKUP(H22,Stores!A:E,5,FALSE) -> Africa | H22: ST-002 | I22: Physical Store | J22: 1 | K22: 969.03 | L22: 0.02 | M22: Transfer | N22: 609.39 | O22: =Table1[[#This Row],[Unit_Price]]*Table1[[#This Row],[Quantity]] -> 969.03 | P22: =Table1[[#This Row],[Revenue]]-Table1[[#This Row],[COGS]] -> 359.64 | Q22: =Table1[[#This Row],[Profit]]/Table1[[#This Row],[Revenue]] -> 0.37113402 | R22: =Table1[[#This Row],[Cost Price]]*Table1[[#This Row],[Quantity]] -> 609.39
A23: ORD-10022 | B23: 46268 | C23: CUST-00072 | D23: =VLOOKUP(C23,Customers!A:E,5,FALSE) -> Mass Market | E23: PROD-0043 | F23: =VLOOKUP(Table1[[#This Row],[Product_ID]],Products!A:D,4,FALSE) -> Audio | G23: =VLOOKUP(H23,Stores!A:E,5,FALSE) -> Europe | H23: ST-011 | I23: Physical Store | J23: 3 | K23: 307.97 | L23: 0 | M23: Transfer | N23: 191.36 | O23: =Table1[[#This Row],[Unit_Price]]*Table1[[#This Row],[Quantity]] -> 923.91 | P23: =Table1[[#This Row],[Revenue]]-Table1[[#This Row],[COGS]] -> 349.83 | Q23: =Table1[[#This Row],[Profit]]/Table1[[#This Row],[Revenue]] -> 0.37864078 | R23: =Table1[[#This Row],[Cost Price]]*Table1[[#This Row],[Quantity]] -> 574.08
A24: ORD-10023 | B24: 46129 | C24: CUST-00317 | D24: =VLOOKUP(C24,Customers!A:E,5,FALSE) -> Mass Market | E24: PROD-0043 | F24: =VLOOKUP(Table1[[#This Row],[Product_ID]],Products!A:D,4,FALSE) -> Audio | G24: =VLOOKUP(H24,Stores!A:E,5,FALSE) -> North America | H24: ST-014 | I24: Physical Store | J24: 2 | K24: 304.98 | L24: 0.05 | M24: Transfer | N24: 191.36 | O24: =Table1[[#This Row],[Unit_Price]]*Table1[[#This Row],[Quantity]] -> 609.96 | P24: =Table1[[#This Row],[Revenue]]-Table1[[#This Row],[COGS]] -> 227.24 | Q24: =Table1[[#This Row],[Profit]]/Table1[[#This Row],[Revenue]] -> 0.37254902 | R24: =Table1[[#This Row],[Cost Price]]*Table1[[#This Row],[Quantity]] -> 382.72
A25: ORD-10024 | B25: 45787 | C25: CUST-00197 | D25: =VLOOKUP(C25,Customers!A:E,5,FALSE) -> Mass Market | E25: PROD-0027 | F25: =VLOOKUP(Table1[[#This Row],[Product_ID]],Products!A:D,4,FALSE) -> Laptops | G25: =VLOOKUP(H25,Stores!A:E,5,FALSE) -> EUROPE | H25: ST-013 | I25: Online | J25: 3 | K25: 1357.03 | L25: 0.05 | M25: Transfer | N25: 853.39 | O25: =Table1[[#This Row],[Unit_Price]]*Table1[[#This Row],[Quantity]] -> 4071.09 | P25: =Table1[[#This Row],[Revenue]]-Table1[[#This Row],[COGS]] -> 1510.92 | Q25: =Table1[[#This Row],[Profit]]/Table1[[#This Row],[Revenue]] -> 0.37113402 | R25: =Table1[[#This Row],[Cost Price]]*Table1[[#This Row],[Quantity]] -> 2560.17
A26: ORD-10025 | B26: 46239 | C26: CUST-00001 | D26: =VLOOKUP(C26,Customers!A:E,5,FALSE) -> Mass Market | E26: PROD-0020 | F26: =VLOOKUP(Table1[[#This Row],[Product_ID]],Products!A:D,4,FALSE) -> Smartphones | G26: =VLOOKUP(H26,Stores!A:E,5,FALSE) -> Asia | H26: ST-010 | I26: Online | J26: 2 | K26: 410.97 | L26: 0.1 | M26: Transfer | N26: 287.28 | O26: =Table1[[#This Row],[Unit_Price]]*Table1[[#This Row],[Quantity]] -> 821.94 | P26: =Table1[[#This Row],[Revenue]]-Table1[[#This Row],[COGS]] -> 247.38 | Q26: =Table1[[#This Row],[Profit]]/Table1[[#This Row],[Revenue]] -> 0.30097087 | R26: =Table1[[#This Row],[Cost Price]]*Table1[[#This Row],[Quantity]] -> 574.56
... A49: ORD-10048 | B49: 46204 | C49: CUST-00111 | D49: =VLOOKUP(C49,Customers!A:E,5,FALSE) -> Mass Market | E49: PROD-0038 | F49: =VLOOKUP(Table1[[#This Row],[Product_ID]],Products!A:D,4,FALSE) -> Audio | G49: =VLOOKUP(H49,Stores!A:E,5,FALSE) -> Africa | H49: ST-001 | I49: Physical Store | J49: 3 | K49: 253.98 | L49: 0.15 | M49: Transfer | N49: 171.81 | O49: =Table1[[#This Row],[Unit_Price]]*Table1[[#This Row],[Quantity]] -> 761.94 | P49: =Table1[[#This Row],[Revenue]]-Table1[[#This Row],[COGS]] -> 246.51 | Q49: =Table1[[#This Row],[Profit]]/Table1[[#This Row],[Revenue]] -> 0.32352941 | R49: =Table1[[#This Row],[Cost Price]]*Table1[[#This Row],[Quantity]] -> 515.43
A50: ORD-10049 | B50: 45941 | C50: CUST-00078 | D50: =VLOOKUP(C50,Customers!A:E,5,FALSE) -> Mass Market | E50: Unknown- 002 | F50: =VLOOKUP(Table1[[#This Row],[Product_ID]],Products!A:D,4,FALSE) -> #N/A | G50: =VLOOKUP(H50,Stores!A:E,5,FALSE) -> Asia | H50: ST-008 | I50: Online | J50: 3 | K50: 375779 | L50: 0.05 | M50: Transfer | N50: 0 | O50: 0 | P50: =Table1[[#This Row],[Revenue]]-Table1[[#This Row],[COGS]] -> 0 | Q50: 0 | R50: =Table1[[#This Row],[Cost Price]]*Table1[[#This Row],[Quantity]] -> 0
A51: ORD-10050 | B51: 45667 | C51: CUST-00580 | D51: =VLOOKUP(C51,Customers!A:E,5,FALSE) -> Mass Affluent | E51: PROD-0051 | F51: =VLOOKUP(Table1[[#This Row],[Product_ID]],Products!A:D,4,FALSE) -> Accessories | G51: =VLOOKUP(H51,Stores!A:E,5,FALSE) -> Africa | H51: ST-002 | I51: Physical Store | J51: 3 | K51: 86.33 | L51: 0.1 | M51: Card | N51: 55.18 | O51: =Table1[[#This Row],[Unit_Price]]*Table1[[#This Row],[Quantity]] -> 258.99 | P51: =Table1[[#This Row],[Revenue]]-Table1[[#This Row],[COGS]] -> 93.45 | Q51: =Table1[[#This Row],[Profit]]/Table1[[#This Row],[Revenue]] -> 0.36082474 | R51: =Table1[[#This Row],[Cost Price]]*Table1[[#This Row],[Quantity]] -> 165.54
A52: ORD-10051 | B52: 46129 | C52: CUST-00664 | D52: =VLOOKUP(C52,Customers!A:E,5,FALSE) -> Premium | E52: PROD-0022 | F52: =VLOOKUP(Table1[[#This Row],[Product_ID]],Products!A:D,4,FALSE) -> Smartphones | G52: =VLOOKUP(H52,Stores!A:E,5,FALSE) -> Africa | H52: ST-001 | I52: Physical Store | J52: 4 | K52: 1286.01 | L52: 0 | M52: Transfer | N52: 883.32 | O52: =Table1[[#This Row],[Unit_Price]]*Table1[[#This Row],[Quantity]] -> 5144.04 | P52: =Table1[[#This Row],[Revenue]]-Table1[[#This Row],[COGS]] -> 1610.76 | Q52: =Table1[[#This Row],[Profit]]/Table1[[#This Row],[Revenue]] -> 0.31313131 | R52: =Table1[[#This Row],[Cost Price]]*Table1[[#This Row],[Quantity]] -> 3533.28
A53: ORD-10052 | B53: 46055 | C53: CUST-00651 | D53: =VLOOKUP(C53,Customers!A:E,5,FALSE) -> Mass Affluent | E53: PROD-0058 | F53: =VLOOKUP(Table1[[#This Row],[Product_ID]],Products!A:D,4,FALSE) -> Accessories | G53: =VLOOKUP(H53,Stores!A:E,5,FALSE) -> North America | H53: ST-015 | I53: Online | J53: 2 | K53: 80.58 | L53: 0.05 | M53: Transfer | N53: 54.51 | O53: =Table1[[#This Row],[Unit_Price]]*Table1[[#This Row],[Quantity]] -> 161.16 | P53: =Table1[[#This Row],[Revenue]]-Table1[[#This Row],[COGS]] -> 52.14 | Q53: =Table1[[#This Row],[Profit]]/Table1[[#This Row],[Revenue]] -> 0.32352941 | R53: =Table1[[#This Row],[Cost Price]]*Table1[[#This Row],[Quantity]] -> 109.02
A54: ORD-10053 | B54: 46086 | C54: CUST-00794 | D54: =VLOOKUP(C54,Customers!A:E,5,FALSE) -> Mass Affluent | E54: PROD-0031 | F54: =VLOOKUP(Table1[[#This Row],[Product_ID]],Products!A:D,4,FALSE) -> Laptops | G54: =VLOOKUP(H54,Stores!A:E,5,FALSE) -> North America | H54: ST-015 | I54: Physical Store | J54: 4 | K54: 1599 | L54: 0.05 | M54: Transfer | N54: 991.38 | O54: =Table1[[#This Row],[Unit_Price]]*Table1[[#This Row],[Quantity]] -> 6396 | P54: =Table1[[#This Row],[Revenue]]-Table1[[#This Row],[COGS]] -> 2430.48 | Q54: =Table1[[#This Row],[Profit]]/Table1[[#This Row],[Revenue]] -> 0.38 | R54: =Table1[[#This Row],[Cost Price]]*Table1[[#This Row],[Quantity]] -> 3965.52
A55: ORD-10054 | B55: 45759 | C55: CUST-00089 | D55: =VLOOKUP(C55,Customers!A:E,5,FALSE) -> VIP | E55: PROD-0018 | F55: =VLOOKUP(Table1[[#This Row],[Product_ID]],Products!A:D,4,FALSE) -> Smartphones | G55: =VLOOKUP(H55,Stores!A:E,5,FALSE) -> North America | H55: ST-015 | I55: Online | J55: 4 | K55: 874.47 | L55: 0.15 | M55: Transfer | N55: 585.81 | O55: =Table1[[#This Row],[Unit_Price]]*Table1[[#This Row],[Quantity]] -> 3497.88 | P55: =Table1[[#This Row],[Revenue]]-Table1[[#This Row],[COGS]] -> 1154.64 | Q55: =Table1[[#This Row],[Profit]]/Table1[[#This Row],[Revenue]] -> 0.33009709 | R55: =Table1[[#This Row],[Cost Price]]*Table1[[#This Row],[Quantity]] -> 2343.24
A56: ORD-10055 | B56: 45884 | C56: CUST-00507 | D56: =VLOOKUP(C56,Customers!A:E,5,FALSE) -> Mass Market | E56: PROD-0055 | F56: =VLOOKUP(Table1[[#This Row],[Product_ID]],Products!A:D,4,FALSE) -> Accessories | G56: =VLOOKUP(H56,Stores!A:E,5,FALSE) -> Europe | H56: ST-011 | I56: Online | J56: 2 | K56: 97.02 | L56: 0.1 | M56: Transfer | N56: 65.34 | O56: =Table1[[#This Row],[Unit_Price]]*Table1[[#This Row],[Quantity]] -> 194.04 | P56: =Table1[[#This Row],[Revenue]]-Table1[[#This Row],[COGS]] -> 63.36 | Q56: =Table1[[#This Row],[Profit]]/Table1[[#This Row],[Revenue]] -> 0.32653061 | R56: =Table1[[#This Row],[Cost Price]]*Table1[[#This Row],[Quantity]] -> 130.68
A57: ORD-10056 | B57: 46044 | C57: CUST-00287 | D57: =VLOOKUP(C57,Customers!A:E,5,FALSE) -> VIP | E57: PROD-0057 | F57: =VLOOKUP(Table1[[#This Row],[Product_ID]],Products!A:D,4,FALSE) -> Accessories | G57: =VLOOKUP(H57,Stores!A:E,5,FALSE) -> oceania | H57: ST-020 | I57: Physical Store | J57: 3 | K57: 127.71 | L57: 0.02 | M57: Card | N57: 78.69 | O57: =Table1[[#This Row],[Unit_Price]]*Table1[[#This Row],[Quantity]] -> 383.13 | P57: =Table1[[#This Row],[Revenue]]-Table1[[#This Row],[COGS]] -> 147.06 | Q57: =Table1[[#This Row],[Profit]]/Table1[[#This Row],[Revenue]] -> 0.38383838 | R57: =Table1[[#This Row],[Cost Price]]*Table1[[#This Row],[Quantity]] -> 236.07
A58: ORD-10057 | B58: 45700 | C58: CUST-00738 | D58: =VLOOKUP(C58,Customers!A:E,5,FALSE) -> Mass Affluent | E58: PROD-0027 | F58: =VLOOKUP(Table1[[#This Row],[Product_ID]],Products!A:D,4,FALSE) -> Laptops | G58: =VLOOKUP(H58,Stores!A:E,5,FALSE) -> North America | H58: ST-016 | I58: Online | J58: 3 | K58: 1399 | L58: 0.2 | M58: Transfer | N58: 853.39 | O58: =Table1[[#This Row],[Unit_Price]]*Table1[[#This Row],[Quantity]] -> 4197 | P58: =Table1[[#This Row],[Revenue]]-Table1[[#This Row],[COGS]] -> 1636.83 | Q58: =Table1[[#This Row],[Profit]]/Table1[[#This Row],[Revenue]] -> 0.39 | R58: =Table1[[#This Row],[Cost Price]]*Table1[[#This Row],[Quantity]] -> 2560.17
A59: ORD-10058 | B59: 45908 | C59: CUST-00096 | D59: =VLOOKUP(C59,Customers!A:E,5,FALSE) -> MASS MARKET | E59: PROD-0019 | F59: =VLOOKUP(Table1[[#This Row],[Product_ID]],Products!A:D,4,FALSE) -> Smartphones | G59: =VLOOKUP(H59,Stores!A:E,5,FALSE) -> Asia | H59: ST-008 | I59: Physical Store | J59: 3 | K59: 301.99 | L59: 0.05 | M59: Transfer | N59: 194.35 | O59: =Table1[[#This Row],[Unit_Price]]*Table1[[#This Row],[Quantity]] -> 905.97 | P59: =Table1[[#This Row],[Revenue]]-Table1[[#This Row],[COGS]] -> 322.92 | Q59: =Table1[[#This Row],[Profit]]/Table1[[#This Row],[Revenue]] -> 0.35643564 | R59: =Table1[[#This Row],[Cost Price]]*Table1[[#This Row],[Quantity]] -> 583.05
A60: ORD-10059 | B60: 46144 | C60: CUST-00485 | D60: Unknown-2 | E60: PROD-0036 | F60: =VLOOKUP(Table1[[#This Row],[Product_ID]],Products!A:D,4,FALSE) -> Laptops | G60: =VLOOKUP(H60,Stores!A:E,5,FALSE) -> South America | H60: ST-017 | I60: Physical Store | J60: 2 | K60: 1187.01 | L60: 0.1 | M60: Transfer | N60: 875.27 | O60: =Table1[[#This Row],[Unit_Price]]*Table1[[#This Row],[Quantity]] -> 2374.02 | P60: =Table1[[#This Row],[Revenue]]-Table1[[#This Row],[COGS]] -> 623.48 | Q60: =Table1[[#This Row],[Profit]]/Table1[[#This Row],[Revenue]] -> 0.26262626 | R60: =Table1[[#This Row],[Cost Price]]*Table1[[#This Row],[Quantity]] -> 1750.54
A61: ORD-10060 | B61: 46229 | C61: CUST-00465 | D61: =VLOOKUP(C61,Customers!A:E,5,FALSE) -> Mass Market | E61: PROD-0018 | F61: =VLOOKUP(Table1[[#This Row],[Product_ID]],Products!A:D,4,FALSE) -> Smartphones | G61: =VLOOKUP(H61,Stores!A:E,5,FALSE) -> Asia | H61: ST-010 | I61: Physical Store | J61: 1 | K61: 832.02 | L61: 0.02 | M61: Transfer | N61: 585.81 | O61: =Table1[[#This Row],[Unit_Price]]*Table1[[#This Row],[Quantity]] -> 832.02 | P61: =Table1[[#This Row],[Revenue]]-Table1[[#This Row],[COGS]] -> 246.21 | Q61: =Table1[[#This Row],[Profit]]/Table1[[#This Row],[Revenue]] -> 0.29591837 | R61: =Table1[[#This Row],[Cost Price]]*Table1[[#This Row],[Quantity]] -> 585.81
A62: ORD-10061 | B62: 45667 | C62: CUST-00761 | D62: =VLOOKUP(C62,Customers!A:E,5,FALSE) -> Premium | E62: PROD-0035 | F62: =VLOOKUP(Table1[[#This Row],[Product_ID]],Products!A:D,4,FALSE) -> Laptops | G62: =VLOOKUP(H62,Stores!A:E,5,FALSE) -> Africa | H62: ST-006 | I62: Online | J62: 1 | K62: 1018.98 | L62: 0.2 | M62: Transfer | N62: 659.34 | O62: =Table1[[#This Row],[Unit_Price]]*Table1[[#This Row],[Quantity]] -> 1018.98 | P62: =Table1[[#This Row],[Revenue]]-Table1[[#This Row],[COGS]] -> 359.64 | Q62: =Table1[[#This Row],[Profit]]/Table1[[#This Row],[Revenue]] -> 0.35294118 | R62: =Table1[[#This Row],[Cost Price]]*Table1[[#This Row],[Quantity]] -> 659.34
A63: ORD-10062 | B63: 46171 | C63: CUST-00779 | D63: =VLOOKUP(C63,Customers!A:E,5,FALSE) -> Mass Affluent | E63: PROD-0034 | F63: =VLOOKUP(Table1[[#This Row],[Product_ID]],Products!A:D,4,FALSE) -> Laptops | G63: =VLOOKUP(H63,Stores!A:E,5,FALSE) -> oceania | H63: ST-020 | I63: Physical Store | J63: 8 | K63: 705.99 | L63: 0.02 | M63: Transfer | N63: 496.29 | O63: =Table1[[#This Row],[Unit_Price]]*Table1[[#This Row],[Quantity]] -> 5647.92 | P63: =Table1[[#This Row],[Revenue]]-Table1[[#This Row],[COGS]] -> 1677.6 | Q63: =Table1[[#This Row],[Profit]]/Table1[[#This Row],[Revenue]] -> 0.2970297 | R63: =Table1[[#This Row],[Cost Price]]*Table1[[#This Row],[Quantity]] -> 3970.32
A64: ORD-10063 | B64: 45986 | C64: CUST-00370 | D64: =VLOOKUP(C64,Customers!A:E,5,FALSE) -> Premium | E64: PROD-0012 | F64: =VLOOKUP(Table1[[#This Row],[Product_ID]],Products!A:D,4,FALSE) -> Televisions | G64: =VLOOKUP(H64,Stores!A:E,5,FALSE) -> Asia | H64: ST-010 | I64: Online | J64: 4 | K64: 2140.98 | L64: 0 | M64: Transfer | N64: 1427.32 | O64: =Table1[[#This Row],[Unit_Price]]*Table1[[#This Row],[Quantity]] -> 8563.92 | P64: =Table1[[#This Row],[Revenue]]-Table1[[#This Row],[COGS]] -> 2854.64 | Q64: =Table1[[#This Row],[Profit]]/Table1[[#This Row],[Revenue]] -> 0.33333333 | R64: =Table1[[#This Row],[Cost Price]]*Table1[[#This Row],[Quantity]] -> 5709.28
A65: ORD-10064 | B65: 45893 | C65: CUST-00056 | D65: =VLOOKUP(C65,Customers!A:E,5,FALSE) -> Mass Affluent | E65: PROD-0036 | F65: =VLOOKUP(Table1[[#This Row],[Product_ID]],Products!A:D,4,FALSE) -> Laptops | G65: =VLOOKUP(H65,Stores!A:E,5,FALSE) -> Asia | H65: ST-010 | I65: Online | J65: 3 | K65: 1175.02 | L65: 0.2 | M65: Card | N65: 875.27 | O65: =Table1[[#This Row],[Unit_Price]]*Table1[[#This Row],[Quantity]] -> 3525.06 | P65: =Table1[[#This Row],[Revenue]]-Table1[[#This Row],[COGS]] -> 899.25 | Q65: =Table1[[#This Row],[Profit]]/Table1[[#This Row],[Revenue]] -> 0.25510204 | R65: =Table1[[#This Row],[Cost Price]]*Table1[[#This Row],[Quantity]] -> 2625.81
A66: ORD-10065 | B66: 45846 | C66: CUST-00588 | D66: =VLOOKUP(C66,Customers!A:E,5,FALSE) -> Mass Affluent | E66: PROD-0019 | F66: =VLOOKUP(Table1[[#This Row],[Product_ID]],Products!A:D,4,FALSE) -> Smartphones | G66: =VLOOKUP(H66,Stores!A:E,5,FALSE) -> North America | H66: ST-016 | I66: Physical Store | J66: 2 | K66: 293.02 | L66: 0 | M66: Card | N66: 194.35 | O66: =Table1[[#This Row],[Unit_Price]]*Table1[[#This Row],[Quantity]] -> 586.04 | P66: =Table1[[#This Row],[Revenue]]-Table1[[#This Row],[COGS]] -> 197.34 | Q66: =Table1[[#This Row],[Profit]]/Table1[[#This Row],[Revenue]] -> 0.33673469 | R66: =Table1[[#This Row],[Cost Price]]*Table1[[#This Row],[Quantity]] -> 388.7
A67: ORD-10066 | B67: 45881 | C67: CUST-00490 | D67: =VLOOKUP(C67,Customers!A:E,5,FALSE) -> Mass Market | E67: PROD-0008 | F67: =VLOOKUP(Table1[[#This Row],[Product_ID]],Products!A:D,4,FALSE) -> Televisions | G67: =VLOOKUP(H67,Stores!A:E,5,FALSE) -> Africa | H67: ST-003 | I67: Physical Store | J67: 2 | K67: 2253.02 | L67: 0 | M67: Cash | N67: 1586.31 | O67: =Table1[[#This Row],[Unit_Price]]*Table1[[#This Row],[Quantity]] -> 4506.04 | P67: =Table1[[#This Row],[Revenue]]-Table1[[#This Row],[COGS]] -> 1333.42 | Q67: =Table1[[#This Row],[Profit]]/Table1[[#This Row],[Revenue]] -> 0.29591837 | R67: =Table1[[#This Row],[Cost Price]]*Table1[[#This Row],[Quantity]] -> 3172.62
A68: ORD-10067 | B68: 45946 | C68: CUST-00577 | D68: =VLOOKUP(C68,Customers!A:E,5,FALSE) -> Mass Market | E68: PROD-0020 | F68: =VLOOKUP(Table1[[#This Row],[Product_ID]],Products!A:D,4,FALSE) -> Smartphones | G68: =VLOOKUP(H68,Stores!A:E,5,FALSE) -> Africa | H68: ST-003 | I68: Online | J68: 1 | K68: 402.99 | L68: 0.15 | M68: Transfer | N68: 287.28 | O68: =Table1[[#This Row],[Unit_Price]]*Table1[[#This Row],[Quantity]] -> 402.99 | P68: =Table1[[#This Row],[Revenue]]-Table1[[#This Row],[COGS]] -> 115.71 | Q68: =Table1[[#This Row],[Profit]]/Table1[[#This Row],[Revenue]] -> 0.28712871 | R68: =Table1[[#This Row],[Cost Price]]*Table1[[#This Row],[Quantity]] -> 287.28
A69: ORD-10068 | B69: 46059 | C69: CUST-00634 | D69: =VLOOKUP(C69,Customers!A:E,5,FALSE) -> Mass Market | E69: PROD-0015 | F69: =VLOOKUP(Table1[[#This Row],[Product_ID]],Products!A:D,4,FALSE) -> Smartphones | G69: =VLOOKUP(H69,Stores!A:E,5,FALSE) -> South America | H69: ST-017 | I69: Physical Store | J69: 2 | K69: 565.47 | L69: 0.2 | M69: Transfer | N69: 362.34 | O69: =Table1[[#This Row],[Unit_Price]]*Table1[[#This Row],[Quantity]] -> 1130.94 | P69: =Table1[[#This Row],[Revenue]]-Table1[[#This Row],[COGS]] -> 406.26 | Q69: =Table1[[#This Row],[Profit]]/Table1[[#This Row],[Revenue]] -> 0.3592233 | R69: =Table1[[#This Row],[Cost Price]]*Table1[[#This Row],[Quantity]] -> 724.68
A70: ORD-10069 | B70: 46171 | C70: CUST-00440 | D70: =VLOOKUP(C70,Customers!A:E,5,FALSE) -> Mass Market | E70: PROD-0020 | F70: =VLOOKUP(Table1[[#This Row],[Product_ID]],Products!A:D,4,FALSE) -> Smartphones | G70: =VLOOKUP(H70,Stores!A:E,5,FALSE) -> Oceania | H70: ST-019 | I70: Online | J70: 3 | K70: 406.98 | L70: 0 | M70: Cash | N70: 287.28 | O70: =Table1[[#This Row],[Unit_Price]]*Table1[[#This Row],[Quantity]] -> 1220.94 | P70: =Table1[[#This Row],[Revenue]]-Table1[[#This Row],[COGS]] -> 359.1 | Q70: =Table1[[#This Row],[Profit]]/Table1[[#This Row],[Revenue]] -> 0.29411765 | R70: =Table1[[#This Row],[Cost Price]]*Table1[[#This Row],[Quantity]] -> 861.84
A71: ORD-10070 | B71: 46190 | C71: CUST-00217 | D71: =VLOOKUP(C71,Customers!A:E,5,FALSE) -> Affluent | E71: PROD-0017 | F71: =VLOOKUP(Table1[[#This Row],[Product_ID]],Products!A:D,4,FALSE) -> Smartphones | G71: =VLOOKUP(Table1[[#This Row],[Customer_ID]],Customers!A:G,7,FALSE) -> South America | H71: Unknown 001 | I71: Online | J71: 2 | K71: 969.03 | L71: 0 | M71: Cash | N71: 609.39 | O71: =Table1[[#This Row],[Unit_Price]]*Table1[[#This Row],[Quantity]] -> 1938.06 | P71: =Table1[[#This Row],[Revenue]]-Table1[[#This Row],[COGS]] -> 719.28 | Q71: =Table1[[#This Row],[Profit]]/Table1[[#This Row],[Revenue]] -> 0.37113402 | R71: =Table1[[#This Row],[Cost Price]]*Table1[[#This Row],[Quantity]] -> 1218.78
A72: ORD-10071 | B72: 45696 | C72: CUST-00419 | D72: =VLOOKUP(C72,Customers!A:E,5,FALSE) -> Affluent | E72: PROD-0029 | F72: =VLOOKUP(Table1[[#This Row],[Product_ID]],Products!A:D,4,FALSE) -> Laptops | G72: =VLOOKUP(H72,Stores!A:E,5,FALSE) -> oceania | H72: ST-020 | I72: Physical Store | J72: 2 | K72: 1528.98 | L72: 0.02 | M72: Transfer | N72: 974.35 | O72: =Table1[[#This Row],[Unit_Price]]*Table1[[#This Row],[Quantity]] -> 3057.96 | P72: =Table1[[#This Row],[Revenue]]-Table1[[#This Row],[COGS]] -> 1109.26 | Q72: =Table1[[#This Row],[Profit]]/Table1[[#This Row],[Revenue]] -> 0.3627451 | R72: =Table1[[#This Row],[Cost Price]]*Table1[[#This Row],[Quantity]] -> 1948.7
A73: ORD-10072 | B73: 46231 | C73: CUST-00290 | D73: =VLOOKUP(C73,Customers!A:E,5,FALSE) -> Mass Market | E73: PROD-0045 | F73: =VLOOKUP(Table1[[#This Row],[Product_ID]],Products!A:D,4,FALSE) -> Audio | G73: =VLOOKUP(H73,Stores!A:E,5,FALSE) -> North America | H73: ST-015 | I73: Online | J73: 3 | K73: 395.01 | L73: 0.05 | M73: Transfer | N73: 263.34 | O73: =Table1[[#This Row],[Unit_Price]]*Table1[[#This Row],[Quantity]] -> 1185.03 | P73: =Table1[[#This Row],[Revenue]]-Table1[[#This Row],[COGS]] -> 395.01 | Q73: =Table1[[#This Row],[Profit]]/Table1[[#This Row],[Revenue]] -> 0.33333333 | R73: =Table1[[#This Row],[Cost Price]]*Table1[[#This Row],[Quantity]] -> 790.02
A74: ORD-10073 | B74: 46149 | C74: CUST-00203 | D74: =VLOOKUP(C74,Customers!A:E,5,FALSE) -> Mass Market | E74: PROD-0028 | F74: =VLOOKUP(Table1[[#This Row],[Product_ID]],Products!A:D,4,FALSE) -> Laptops | G74: =VLOOKUP(H74,Stores!A:E,5,FALSE) -> Africa | H74: ST-004 | I74: Online | J74: 3 | K74: 1028.97 | L74: 0.05 | M74: Cash | N74: 689.31 | O74: =Table1[[#This Row],[Unit_Price]]*Table1[[#This Row],[Quantity]] -> 3086.91 | P74: =Table1[[#This Row],[Revenue]]-Table1[[#This Row],[COGS]] -> 1018.98 | Q74: =Table1[[#This Row],[Profit]]/Table1[[#This Row],[Revenue]] -> 0.33009709 | R74: =Table1[[#This Row],[Cost Price]]*Table1[[#This Row],[Quantity]] -> 2067.93
A75: ORD-10074 | B75: 45817 | C75: CUST-00062 | D75: =VLOOKUP(C75,Customers!A:E,5,FALSE) -> Mass Affluent | E75: PROD-0011 | F75: =VLOOKUP(Table1[[#This Row],[Product_ID]],Products!A:D,4,FALSE) -> Televisions | G75: =VLOOKUP(H75,Stores!A:E,5,FALSE) -> Asia | H75: ST-010 | I75: Physical Store | J75: 2 | K75: 1861.02 | L75: 0.2 | M75: Transfer | N75: 1177.38 | O75: =Table1[[#This Row],[Unit_Price]]*Table1[[#This Row],[Quantity]] -> 3722.04 | P75: =Table1[[#This Row],[Revenue]]-Table1[[#This Row],[COGS]] -> 1367.28 | Q75: =Table1[[#This Row],[Profit]]/Table1[[#This Row],[Revenue]] -> 0.36734694 | R75: =Table1[[#This Row],[Cost Price]]*Table1[[#This Row],[Quantity]] -> 2354.76
A76: ORD-10075 | B76: 46228 | C76: CUST-00413 | D76: =VLOOKUP(C76,Customers!A:E,5,FALSE) -> Mass Market | E76: PROD-0018 | F76: =VLOOKUP(Table1[[#This Row],[Product_ID]],Products!A:D,4,FALSE) -> Smartphones | G76: =VLOOKUP(H76,Stores!A:E,5,FALSE) -> South America | H76: ST-017 | I76: Physical Store | J76: 2 | K76: 865.98 | L76: 0 | M76: Transfer | N76: 585.81 | O76: =Table1[[#This Row],[Unit_Price]]*Table1[[#This Row],[Quantity]] -> 1731.96 | P76: =Table1[[#This Row],[Revenue]]-Table1[[#This Row],[COGS]] -> 560.34 | Q76: =Table1[[#This Row],[Profit]]/Table1[[#This Row],[Revenue]] -> 0.32352941 | R76: =Table1[[#This Row],[Cost Price]]*Table1[[#This Row],[Quantity]] -> 1171.62
A77: ORD-10076 | B77: 46035 | C77: CUST-00619 | D77: =VLOOKUP(C77,Customers!A:E,5,FALSE) -> Mass Market | E77: PROD-0017 | F77: =VLOOKUP(Table1[[#This Row],[Product_ID]],Products!A:D,4,FALSE) -> Smartphones | G77: =VLOOKUP(H77,Stores!A:E,5,FALSE) -> Africa | H77: ST-001 | I77: Online | J77: 1 | K77: 999 | L77: 0 | M77: Transfer | N77: 609.39 | O77: =Table1[[#This Row],[Unit_Price]]*Table1[[#This Row],[Quantity]] -> 999 | P77: =Table1[[#This Row],[Revenue]]-Table1[[#This Row],[COGS]] -> 389.61 | Q77: =Table1[[#This Row],[Profit]]/Table1[[#This Row],[Revenue]] -> 0.39 | R77: =Table1[[#This Row],[Cost Price]]*Table1[[#This Row],[Quantity]] -> 609.39
A78: ORD-10077 | B78: 46165 | C78: CUST-00042 | D78: =VLOOKUP(C78,Customers!A:E,5,FALSE) -> Mass Market | E78: PROD-0049 | F78: =VLOOKUP(Table1[[#This Row],[Product_ID]],Products!A:D,4,FALSE) -> Accessories | G78: =VLOOKUP(H78,Stores!A:E,5,FALSE) -> Africa | H78: ST-006 | I78: Physical Store | J78: 3 | K78: 68.31 | L78: 0.2 | M78: Transfer | N78: 44.85 | O78: =Table1[[#This Row],[Unit_Price]]*Table1[[#This Row],[Quantity]] -> 204.93 | P78: =Table1[[#This Row],[Revenue]]-Table1[[#This Row],[COGS]] -> 70.38 | Q78: =Table1[[#This Row],[Profit]]/Table1[[#This Row],[Revenue]] -> 0.34343434 | R78: =Table1[[#This Row],[Cost Price]]*Table1[[#This Row],[Quantity]] -> 134.55
A79: ORD-10078 | B79: 45668 | C79: CUST-00600 | D79: =VLOOKUP(C79,Customers!A:E,5,FALSE) -> Affluent | E79: PROD-0028 | F79: =VLOOKUP(Table1[[#This Row],[Product_ID]],Products!A:D,4,FALSE) -> Laptops | G79: =VLOOKUP(H79,Stores!A:E,5,FALSE) -> North America | H79: ST-016 | I79: Online | J79: 2 | K79: 999 | L79: 0.15 | M79: Transfer | N79: 689.31 | O79: =Table1[[#This Row],[Unit_Price]]*Table1[[#This Row],[Quantity]] -> 1998 | P79: =Table1[[#This Row],[Revenue]]-Table1[[#This Row],[COGS]] -> 619.38 | Q79: =Table1[[#This Row],[Profit]]/Table1[[#This Row],[Revenue]] -> 0.31 | R79: =Table1[[#This Row],[Cost Price]]*Table1[[#This Row],[Quantity]] -> 1378.62
A80: ORD-10079 | B80: 46357 | C80: CUST-00687 | D80: =VLOOKUP(C80,Customers!A:E,5,FALSE) -> Mass Affluent | E80: PROD-0007 | F80: =VLOOKUP(Table1[[#This Row],[Product_ID]],Products!A:D,4,FALSE) -> Televisions | G80: =VLOOKUP(H80,Stores!A:E,5,FALSE) -> Africa | H80: ST-006 | I80: Physical Store | J80: 2 | K80: 1781.01 | L80: 0.2 | M80: Transfer | N80: 1097.39 | O80: =Table1[[#This Row],[Unit_Price]]*Table1[[#This Row],[Quantity]] -> 3562.02 | P80: =Table1[[#This Row],[Revenue]]-Table1[[#This Row],[COGS]] -> 1367.24 | Q80: =Table1[[#This Row],[Profit]]/Table1[[#This Row],[Revenue]] -> 0.38383838 | R80: =Table1[[#This Row],[Cost Price]]*Table1[[#This Row],[Quantity]] -> 2194.78
A81: ORD-10080 | B81: 46180 | C81: CUST-00411 | D81: =VLOOKUP(C81,Customers!A:E,5,FALSE) -> Mass Affluent | E81: PROD-0053 | F81: =VLOOKUP(Table1[[#This Row],[Product_ID]],Products!A:D,4,FALSE) -> Accessories | G81: =VLOOKUP(H81,Stores!A:E,5,FALSE) -> South America | H81: ST-018 | I81: Online | J81: 2 | K81: 71.07 | L81: 0.1 | M81: Transfer | N81: 44.16 | O81: =Table1[[#This Row],[Unit_Price]]*Table1[[#This Row],[Quantity]] -> 142.14 | P81: =Table1[[#This Row],[Revenue]]-Table1[[#This Row],[COGS]] -> 53.82 | Q81: =Table1[[#This Row],[Profit]]/Table1[[#This Row],[Revenue]] -> 0.37864078 | R81: =Table1[[#This Row],[Cost Price]]*Table1[[#This Row],[Quantity]] -> 88.32
A82: ORD-10081 | B82: 46035 | C82: CUST-00119 | D82: =VLOOKUP(C82,Customers!A:E,5,FALSE) -> Affluent | E82: PROD-0050 | F82: =VLOOKUP(Table1[[#This Row],[Product_ID]],Products!A:D,4,FALSE) -> Accessories | G82: =VLOOKUP(H82,Stores!A:E,5,FALSE) -> EUROPE | H82: ST-013 | I82: Online | J82: 3 | K82: 122.57 | L82: 0.2 | M82: Transfer | N82: 85.68 | O82: =Table1[[#This Row],[Unit_Price]]*Table1[[#This Row],[Quantity]] -> 367.71 | P82: =Table1[[#This Row],[Revenue]]-Table1[[#This Row],[COGS]] -> 110.67 | Q82: =Table1[[#This Row],[Profit]]/Table1[[#This Row],[Revenue]] -> 0.30097087 | R82: =Table1[[#This Row],[Cost Price]]*Table1[[#This Row],[Quantity]] -> 257.04
A83: ORD-10082 | B83: 45897 | C83: CUST-00193 | D83: =VLOOKUP(C83,Customers!A:E,5,FALSE) -> Mass Market | E83: PROD-0034 | F83: =VLOOKUP(Table1[[#This Row],[Product_ID]],Products!A:D,4,FALSE) -> Laptops | G83: =VLOOKUP(H83,Stores!A:E,5,FALSE) -> Europe | H83: ST-012 | I83: Physical Store | J83: 3 | K83: 678.03 | L83: 0 | M83: Cash | N83: 496.29 | O83: =Table1[[#This Row],[Unit_Price]]*Table1[[#This Row],[Quantity]] -> 2034.09 | P83: =Table1[[#This Row],[Revenue]]-Table1[[#This Row],[COGS]] -> 545.22 | Q83: =Table1[[#This Row],[Profit]]/Table1[[#This Row],[Revenue]] -> 0.26804124 | R83: =Table1[[#This Row],[Cost Price]]*Table1[[#This Row],[Quantity]] -> 1488.87
... A121: ORD-10120 | B121: 46102 | C121: CUST-00094 | D121: =VLOOKUP(C121,Customers!A:E,5,FALSE) -> Mass Market | E121: PROD-0043 | F121: =VLOOKUP(Table1[[#This Row],[Product_ID]],Products!A:D,4,FALSE) -> Audio | G121: =VLOOKUP(H121,Stores!A:E,5,FALSE) -> Asia | H121: ST-007 | I121: Online | J121: 1 | K121: 301.99 | L121: 0.1 | M121: Cash | N121: 191.36 | O121: =Table1[[#This Row],[Unit_Price]]*Table1[[#This Row],[Quantity]] -> 301.99 | P121: =Table1[[#This Row],[Revenue]]-Table1[[#This Row],[COGS]] -> 110.63 | Q121: =Table1[[#This Row],[Profit]]/Table1[[#This Row],[Revenue]] -> 0.36633663 | R121: =Table1[[#This Row],[Cost Price]]*Table1[[#This Row],[Quantity]] -> 191.36
A122: ORD-10121 | B122: 45757 | C122: CUST-00579 | D122: =VLOOKUP(C122,Customers!A:E,5,FALSE) -> Affluent | E122: PROD-0014 | F122: =VLOOKUP(Table1[[#This Row],[Product_ID]],Products!A:D,4,FALSE) -> #N/A | G122: =VLOOKUP(H122,Stores!A:E,5,FALSE) -> Africa | H122: ST-003 | I122: Online | J122: 3 | K122: 771.47 | L122: 0.02 | M122: Transfer | N122: 0 | O122: 0 | P122: =Table1[[#This Row],[Revenue]]-Table1[[#This Row],[COGS]] -> 0 | Q122: 0 | R122: =Table1[[#This Row],[Cost Price]]*Table1[[#This Row],[Quantity]] -> 0
A123: ORD-10122 | B123: 45945 | C123: CUST-00611 | D123: =VLOOKUP(C123,Customers!A:E,5,FALSE) -> Mass Market | E123: PROD-0001 | F123: =VLOOKUP(Table1[[#This Row],[Product_ID]],Products!A:D,4,FALSE) -> Televisions | G123: =VLOOKUP(H123,Stores!A:E,5,FALSE) -> Asia | H123: ST-009 | I123: Online | J123: 8 | K123: 699 | L123: 0.05 | M123: Cash | N123: 433.38 | O123: =Table1[[#This Row],[Unit_Price]]*Table1[[#This Row],[Quantity]] -> 5592 | P123: =Table1[[#This Row],[Revenue]]-Table1[[#This Row],[COGS]] -> 2124.96 | Q123: =Table1[[#This Row],[Profit]]/Table1[[#This Row],[Revenue]] -> 0.38 | R123: =Table1[[#This Row],[Cost Price]]*Table1[[#This Row],[Quantity]] -> 3467.04
A124: ORD-10123 | B124: 45926 | C124: CUST-00677 | D124: =VLOOKUP(C124,Customers!A:E,5,FALSE) -> Premium | E124: PROD-0056 | F124: =VLOOKUP(Table1[[#This Row],[Product_ID]],Products!A:D,4,FALSE) -> Accessories | G124: =VLOOKUP(H124,Stores!A:E,5,FALSE) -> Africa | H124: ST-001 | I124: Online | J124: 1 | K124: 154.23 | L124: 0.02 | M124: Transfer | N124: 116.07 | O124: =Table1[[#This Row],[Unit_Price]]*Table1[[#This Row],[Quantity]] -> 154.23 | P124: =Table1[[#This Row],[Revenue]]-Table1[[#This Row],[COGS]] -> 38.16 | Q124: =Table1[[#This Row],[Profit]]/Table1[[#This Row],[Revenue]] -> 0.24742268 | R124: =Table1[[#This Row],[Cost Price]]*Table1[[#This Row],[Quantity]] -> 116.07
A125: ORD-10124 | B125: 46035 | C125: CUST-00017 | D125: =VLOOKUP(C125,Customers!A:E,5,FALSE) -> Affluent | E125: PROD-0012 | F125: =VLOOKUP(Table1[[#This Row],[Product_ID]],Products!A:D,4,FALSE) -> Televisions | G125: =VLOOKUP(H125,Stores!A:E,5,FALSE) -> Asia | H125: ST-009 | I125: Online | J125: 1 | K125: 2119.99 | L125: 0.35 | M125: Transfer | N125: 1427.32 | O125: =Table1[[#This Row],[Unit_Price]]*Table1[[#This Row],[Quantity]] -> 2119.99 | P125: =Table1[[#This Row],[Revenue]]-Table1[[#This Row],[COGS]] -> 692.67 | Q125: =Table1[[#This Row],[Profit]]/Table1[[#This Row],[Revenue]] -> 0.32673267 | R125: =Table1[[#This Row],[Cost Price]]*Table1[[#This Row],[Quantity]] -> 1427.32
A126: ORD-10126 | B126: 46127 | C126: CUST-00227 | D126: =VLOOKUP(C126,Customers!A:E,5,FALSE) -> Mass Market | E126: PROD-0040 | F126: =VLOOKUP(Table1[[#This Row],[Product_ID]],Products!A:D,4,FALSE) -> Audio | G126: =VLOOKUP(H126,Stores!A:E,5,FALSE) -> Africa | H126: ST-002 | I126: Physical Store | J126: 2 | K126: 98.01 | L126: 0 | M126: Card | N126: 71.28 | O126: =Table1[[#This Row],[Unit_Price]]*Table1[[#This Row],[Quantity]] -> 196.02 | P126: =Table1[[#This Row],[Revenue]]-Table1[[#This Row],[COGS]] -> 53.46 | Q126: =Table1[[#This Row],[Profit]]/Table1[[#This Row],[Revenue]] -> 0.27272727 | R126: =Table1[[#This Row],[Cost Price]]*Table1[[#This Row],[Quantity]] -> 142.56
A127: ORD-10127 | B127: 46085 | C127: CUST-00412 | D127: =VLOOKUP(C127,Customers!A:E,5,FALSE) -> Premium | E127: PROD-0028 | F127: =VLOOKUP(Table1[[#This Row],[Product_ID]],Products!A:D,4,FALSE) -> Laptops | G127: =VLOOKUP(H127,Stores!A:E,5,FALSE) -> Africa | H127: ST-004 | I127: Physical Store | J127: 4 | K127: 1008.99 | L127: 0.2 | M127: Card | N127: 689.31 | O127: =Table1[[#This Row],[Unit_Price]]*Table1[[#This Row],[Quantity]] -> 4035.96 | P127: =Table1[[#This Row],[Revenue]]-Table1[[#This Row],[COGS]] -> 1278.72 | Q127: =Table1[[#This Row],[Profit]]/Table1[[#This Row],[Revenue]] -> 0.31683168 | R127: =Table1[[#This Row],[Cost Price]]*Table1[[#This Row],[Quantity]] -> 2757.24
A128: ORD-10128 | B128: 45970 | C128: CUST-00330 | D128: =VLOOKUP(C128,Customers!A:E,5,FALSE) -> Mass Market | E128: PROD-0039 | F128: =VLOOKUP(Table1[[#This Row],[Product_ID]],Products!A:D,4,FALSE) -> Audio | G128: =VLOOKUP(H128,Stores!A:E,5,FALSE) -> Africa | H128: ST-005 | I128: Online | J128: 1 | K128: 200.99 | L128: 0.1 | M128: Transfer | N128: 129.35 | O128: =Table1[[#This Row],[Unit_Price]]*Table1[[#This Row],[Quantity]] -> 200.99 | P128: =Table1[[#This Row],[Revenue]]-Table1[[#This Row],[COGS]] -> 71.64 | Q128: =Table1[[#This Row],[Profit]]/Table1[[#This Row],[Revenue]] -> 0.35643564 | R128: =Table1[[#This Row],[Cost Price]]*Table1[[#This Row],[Quantity]] -> 129.35
A129: ORD-10129 | B129: 46059 | C129: CUST-00544 | D129: =VLOOKUP(C129,Customers!A:E,5,FALSE) -> Premium | E129: PROD-0019 | F129: =VLOOKUP(Table1[[#This Row],[Product_ID]],Products!A:D,4,FALSE) -> Smartphones | G129: =VLOOKUP(H129,Stores!A:E,5,FALSE) -> North America | H129: ST-015 | I129: Physical Store | J129: 1 | K129: 293.02 | L129: 0 | M129: Transfer | N129: 194.35 | O129: =Table1[[#This Row],[Unit_Price]]*Table1[[#This Row],[Quantity]] -> 293.02 | P129: =Table1[[#This Row],[Revenue]]-Table1[[#This Row],[COGS]] -> 98.67 | Q129: =Table1[[#This Row],[Profit]]/Table1[[#This Row],[Revenue]] -> 0.33673469 | R129: =Table1[[#This Row],[Cost Price]]*Table1[[#This Row],[Quantity]] -> 194.35
A130: ORD-10130 | B130: 45980 | C130: CUST-00441 | D130: =VLOOKUP(C130,Customers!A:E,5,FALSE) -> Mass Affluent | E130: PROD-0029 | F130: =VLOOKUP(Table1[[#This Row],[Product_ID]],Products!A:D,4,FALSE) -> Laptops | G130: =VLOOKUP(H130,Stores!A:E,5,FALSE) -> Asia | H130: ST-008 | I130: Physical Store | J130: 2 | K130: 1484.01 | L130: 0.2 | M130: Transfer | N130: 974.35 | O130: =Table1[[#This Row],[Unit_Price]]*Table1[[#This Row],[Quantity]] -> 2968.02 | P130: =Table1[[#This Row],[Revenue]]-Table1[[#This Row],[COGS]] -> 1019.32 | Q130: =Table1[[#This Row],[Profit]]/Table1[[#This Row],[Revenue]] -> 0.34343434 | R130: =Table1[[#This Row],[Cost Price]]*Table1[[#This Row],[Quantity]] -> 1948.7
A131: ORD-10131 | B131: 46025 | C131: CUST-00748 | D131: =VLOOKUP(C131,Customers!A:E,5,FALSE) -> Premium | E131: PROD-0007 | F131: =VLOOKUP(Table1[[#This Row],[Product_ID]],Products!A:D,4,FALSE) -> Televisions | G131: =VLOOKUP(H131,Stores!A:E,5,FALSE) -> Europe | H131: ST-011 | I131: Physical Store | J131: 2 | K131: 1852.97 | L131: 0.05 | M131: Transfer | N131: 1097.39 | O131: =Table1[[#This Row],[Unit_Price]]*Table1[[#This Row],[Quantity]] -> 3705.94 | P131: =Table1[[#This Row],[Revenue]]-Table1[[#This Row],[COGS]] -> 1511.16 | Q131: =Table1[[#This Row],[Profit]]/Table1[[#This Row],[Revenue]] -> 0.40776699 | R131: =Table1[[#This Row],[Cost Price]]*Table1[[#This Row],[Quantity]] -> 2194.78
A132: ORD-10132 | B132: 45948 | C132: CUST-00704 | D132: =VLOOKUP(C132,Customers!A:E,5,FALSE) -> Mass Market | E132: PROD-0060 | F132: =VLOOKUP(Table1[[#This Row],[Product_ID]],Products!A:D,4,FALSE) -> Accessories | G132: =VLOOKUP(H132,Stores!A:E,5,FALSE) -> North America | H132: ST-016 | I132: Online | J132: 1 | K132: 105.73 | L132: 0 | M132: Card | N132: 78.48 | O132: =Table1[[#This Row],[Unit_Price]]*Table1[[#This Row],[Quantity]] -> 105.73 | P132: =Table1[[#This Row],[Revenue]]-Table1[[#This Row],[COGS]] -> 27.25 | Q132: =Table1[[#This Row],[Profit]]/Table1[[#This Row],[Revenue]] -> 0.25773196 | R132: =Table1[[#This Row],[Cost Price]]*Table1[[#This Row],[Quantity]] -> 78.48
A133: ORD-10133 | B133: 46298 | C133: CUST-00099 | D133: =VLOOKUP(C133,Customers!A:E,5,FALSE) -> Mass Affluent | E133: PROD-0048 | F133: =VLOOKUP(Table1[[#This Row],[Product_ID]],Products!A:D,4,FALSE) -> Audio | G133: =VLOOKUP(H133,Stores!A:E,5,FALSE) -> Europe | H133: ST-012 | I133: Online | J133: 3 | K133: 115.43 | L133: 0.1 | M133: Card | N133: 82.11 | O133: =Table1[[#This Row],[Unit_Price]]*Table1[[#This Row],[Quantity]] -> 346.29 | P133: =Table1[[#This Row],[Revenue]]-Table1[[#This Row],[COGS]] -> 99.96 | Q133: =Table1[[#This Row],[Profit]]/Table1[[#This Row],[Revenue]] -> 0.28865979 | R133: =Table1[[#This Row],[Cost Price]]*Table1[[#This Row],[Quantity]] -> 246.33
A134: ORD-10134 | B134: 46080 | C134: CUST-00363 | D134: =VLOOKUP(C134,Customers!A:E,5,FALSE) -> Mass Market | E134: PROD-0056 | F134: =VLOOKUP(Table1[[#This Row],[Product_ID]],Products!A:D,4,FALSE) -> Accessories | G134: =VLOOKUP(H134,Stores!A:E,5,FALSE) -> North America | H134: ST-014 | I134: Online | J134: 6 | K134: 159 | L134: 0.05 | M134: Transfer | N134: 116.07 | O134: =Table1[[#This Row],[Unit_Price]]*Table1[[#This Row],[Quantity]] -> 954 | P134: =Table1[[#This Row],[Revenue]]-Table1[[#This Row],[COGS]] -> 257.58 | Q134: =Table1[[#This Row],[Profit]]/Table1[[#This Row],[Revenue]] -> 0.27 | R134: =Table1[[#This Row],[Cost Price]]*Table1[[#This Row],[Quantity]] -> 696.42
... A148: ORD-10148 | B148: 45938 | C148: CUST-00471 | D148: =VLOOKUP(C148,Customers!A:E,5,FALSE) -> Affluent | E148: PROD-0059 | F148: =VLOOKUP(Table1[[#This Row],[Product_ID]],Products!A:D,4,FALSE) -> Accessories | G148: =VLOOKUP(H148,Stores!A:E,5,FALSE) -> Africa | H148: ST-003 | I148: Physical Store | J148: 3 | K148: 150.49 | L148: 0.15 | M148: Transfer | N148: 96.85 | O148: =Table1[[#This Row],[Unit_Price]]*Table1[[#This Row],[Quantity]] -> 451.47 | P148: =Table1[[#This Row],[Revenue]]-Table1[[#This Row],[COGS]] -> 160.92 | Q148: =Table1[[#This Row],[Profit]]/Table1[[#This Row],[Revenue]] -> 0.35643564 | R148: =Table1[[#This Row],[Cost Price]]*Table1[[#This Row],[Quantity]] -> 290.55
A149: ORD-10149 | B149: 46018 | C149: CUST-00118 | D149: Unknown-1 | E149: PROD-0026 | F149: =VLOOKUP(Table1[[#This Row],[Product_ID]],Products!A:D,4,FALSE) -> Laptops | G149: =VLOOKUP(H149,Stores!A:E,5,FALSE) -> Africa | H149: ST-001 | I149: Physical Store | J149: 1 | K149: 1682.01 | L149: 0.2 | M149: Transfer | N149: 1240.27 | O149: =Table1[[#This Row],[Unit_Price]]*Table1[[#This Row],[Quantity]] -> 1682.01 | P149: =Table1[[#This Row],[Revenue]]-Table1[[#This Row],[COGS]] -> 441.74 | Q149: =Table1[[#This Row],[Profit]]/Table1[[#This Row],[Revenue]] -> 0.26262626 | R149: =Table1[[#This Row],[Cost Price]]*Table1[[#This Row],[Quantity]] -> 1240.27
A150: ORD-10150 | B150: 45915 | C150: CUST-00448 | D150: =VLOOKUP(C150,Customers!A:E,5,FALSE) -> Mass Market | E150: PROD-0055 | F150: =VLOOKUP(Table1[[#This Row],[Product_ID]],Products!A:D,4,FALSE) -> Accessories | G150: =VLOOKUP(H150,Stores!A:E,5,FALSE) -> Africa | H150: ST-004 | I150: Online | J150: 2 | K150: 97.02 | L150: 0.15 | M150: Transfer | N150: 65.34 | O150: =Table1[[#This Row],[Unit_Price]]*Table1[[#This Row],[Quantity]] -> 194.04 | P150: =Table1[[#This Row],[Revenue]]-Table1[[#This Row],[COGS]] -> 63.36 | Q150: =Table1[[#This Row],[Profit]]/Table1[[#This Row],[Revenue]] -> 0.32653061 | R150: =Table1[[#This Row],[Cost Price]]*Table1[[#This Row],[Quantity]] -> 130.68
A151: ORD-10151 | B151: 45939 | C151: CUST-00406 | D151: =VLOOKUP(C151,Customers!A:E,5,FALSE) -> Mass Market | E151: PROD-0056 | F151: =VLOOKUP(Table1[[#This Row],[Product_ID]],Products!A:D,4,FALSE) -> Accessories | G151: =VLOOKUP(H151,Stores!A:E,5,FALSE) -> Asia | H151: ST-010 | I151: Physical Store | J151: 1 | K151: 163.77 | L151: 0 | M151: Card | N151: 116.07 | O151: =Table1[[#This Row],[Unit_Price]]*Table1[[#This Row],[Quantity]] -> 163.77 | P151: =Table1[[#This Row],[Revenue]]-Table1[[#This Row],[COGS]] -> 47.7 | Q151: =Table1[[#This Row],[Profit]]/Table1[[#This Row],[Revenue]] -> 0.29126214 | R151: =Table1[[#This Row],[Cost Price]]*Table1[[#This Row],[Quantity]] -> 116.07
A152: ORD-10152 | B152: 46131 | C152: CUST-00649 | D152: =VLOOKUP(C152,Customers!A:E,5,FALSE) -> Mass Affluent | E152: PROD-0008 | F152: =VLOOKUP(Table1[[#This Row],[Product_ID]],Products!A:D,4,FALSE) -> Televisions | G152: =VLOOKUP(H152,Stores!A:E,5,FALSE) -> South America | H152: ST-017 | I152: Online | J152: 5 | K152: 2344.98 | L152: 0.1 | M152: Transfer | N152: 1586.31 | O152: =Table1[[#This Row],[Unit_Price]]*Table1[[#This Row],[Quantity]] -> 11724.9 | P152: =Table1[[#This Row],[Revenue]]-Table1[[#This Row],[COGS]] -> 3793.35 | Q152: =Table1[[#This Row],[Profit]]/Table1[[#This Row],[Revenue]] -> 0.32352941 | R152: =Table1[[#This Row],[Cost Price]]*Table1[[#This Row],[Quantity]] -> 7931.55
A153: ORD-10153 | B153: 46200 | C153: CUST-00152 | D153: =VLOOKUP(C153,Customers!A:E,5,FALSE) -> Mass Market | E153: PROD-0016 | F153: =VLOOKUP(Table1[[#This Row],[Product_ID]],Products!A:D,4,FALSE) -> Smartphones | G153: =VLOOKUP(H153,Stores!A:E,5,FALSE) -> Africa | H153: ST-004 | I153: Online | J153: 2 | K153: 705.99 | L153: 0 | M153: Transfer | N153: 510.27 | O153: =Table1[[#This Row],[Unit_Price]]*Table1[[#This Row],[Quantity]] -> 1411.98 | P153: =Table1[[#This Row],[Revenue]]-Table1[[#This Row],[COGS]] -> 391.44 | Q153: =Table1[[#This Row],[Profit]]/Table1[[#This Row],[Revenue]] -> 0.27722772 | R153: =Table1[[#This Row],[Cost Price]]*Table1[[#This Row],[Quantity]] -> 1020.54
A154: ORD-10154 | B154: 45948 | C154: CUST-00779 | D154: =VLOOKUP(C154,Customers!A:E,5,FALSE) -> Mass Affluent | E154: PROD-0049 | F154: =VLOOKUP(Table1[[#This Row],[Product_ID]],Products!A:D,4,FALSE) -> Accessories | G154: =VLOOKUP(H154,Stores!A:E,5,FALSE) -> Africa | H154: ST-003 | I154: Online | J154: 6 | K154: 67.62 | L154: 0.2 | M154: Transfer | N154: 44.85 | O154: =Table1[[#This Row],[Unit_Price]]*Table1[[#This Row],[Quantity]] -> 405.72 | P154: =Table1[[#This Row],[Revenue]]-Table1[[#This Row],[COGS]] -> 136.62 | Q154: =Table1[[#This Row],[Profit]]/Table1[[#This Row],[Revenue]] -> 0.33673469 | R154: =Table1[[#This Row],[Cost Price]]*Table1[[#This Row],[Quantity]] -> 269.1
A155: ORD-10155 | B155: 46158 | C155: CUST-00779 | D155: =VLOOKUP(C155,Customers!A:E,5,FALSE) -> Mass Affluent | E155: PROD-0038 | F155: =VLOOKUP(Table1[[#This Row],[Product_ID]],Products!A:D,4,FALSE) -> Audio | G155: =VLOOKUP(H155,Stores!A:E,5,FALSE) -> North America | H155: ST-015 | I155: Physical Store | J155: 5 | K155: 256.47 | L155: 0.1 | M155: Cash | N155: 171.81 | O155: =Table1[[#This Row],[Unit_Price]]*Table1[[#This Row],[Quantity]] -> 1282.35 | P155: =Table1[[#This Row],[Revenue]]-Table1[[#This Row],[COGS]] -> 423.3 | Q155: =Table1[[#This Row],[Profit]]/Table1[[#This Row],[Revenue]] -> 0.33009709 | R155: =Table1[[#This Row],[Cost Price]]*Table1[[#This Row],[Quantity]] -> 859.05
A156: ORD-10156 | B156: 46095 | C156: CUST-00070 | D156: =VLOOKUP(C156,Customers!A:E,5,FALSE) -> Affluent | E156: PROD-0031 | F156: =VLOOKUP(Table1[[#This Row],[Product_ID]],Products!A:D,4,FALSE) -> Laptops | G156: =VLOOKUP(H156,Stores!A:E,5,FALSE) -> North America | H156: ST-015 | I156: Physical Store | J156: 4 | K156: 1567.02 | L156: 0.05 | M156: Transfer | N156: 991.38 | O156: =Table1[[#This Row],[Unit_Price]]*Table1[[#This Row],[Quantity]] -> 6268.08 | P156: =Table1[[#This Row],[Revenue]]-Table1[[#This Row],[COGS]] -> 2302.56 | Q156: =Table1[[#This Row],[Profit]]/Table1[[#This Row],[Revenue]] -> 0.36734694 | R156: =Table1[[#This Row],[Cost Price]]*Table1[[#This Row],[Quantity]] -> 3965.52
A157: ORD-10157 | B157: 46129 | C157: CUST-00076 | D157: =VLOOKUP(C157,Customers!A:E,5,FALSE) -> mass market | E157: PROD-0020 | F157: =VLOOKUP(Table1[[#This Row],[Product_ID]],Products!A:D,4,FALSE) -> Smartphones | G157: =VLOOKUP(H157,Stores!A:E,5,FALSE) -> North America | H157: ST-015 | I157: Physical Store | J157: 1 | K157: 399 | L157: 0.1 | M157: Transfer | N157: 287.28 | O157: =Table1[[#This Row],[Unit_Price]]*Table1[[#This Row],[Quantity]] -> 399 | P157: =Table1[[#This Row],[Revenue]]-Table1[[#This Row],[COGS]] -> 111.72 | Q157: =Table1[[#This Row],[Profit]]/Table1[[#This Row],[Revenue]] -> 0.28 | R157: =Table1[[#This Row],[Cost Price]]*Table1[[#This Row],[Quantity]] -> 287.28
A158: ORD-10158 | B158: 45909 | C158: CUST-00661 | D158: =VLOOKUP(C158,Customers!A:E,5,FALSE) -> Affluent | E158: PROD-0056 | F158: =VLOOKUP(Table1[[#This Row],[Product_ID]],Products!A:D,4,FALSE) -> Accessories | G158: =VLOOKUP(H158,Stores!A:E,5,FALSE) -> Africa | H158: ST-003 | I158: Physical Store | J158: 2 | K158: 162.18 | L158: 0 | M158: Transfer | N158: 116.07 | O158: =Table1[[#This Row],[Unit_Price]]*Table1[[#This Row],[Quantity]] -> 324.36 | P158: =Table1[[#This Row],[Revenue]]-Table1[[#This Row],[COGS]] -> 92.22 | Q158: =Table1[[#This Row],[Profit]]/Table1[[#This Row],[Revenue]] -> 0.28431373 | R158: =Table1[[#This Row],[Cost Price]]*Table1[[#This Row],[Quantity]] -> 232.14
A159: ORD-10159 | B159: 46162 | C159: CUST-00668 | D159: =VLOOKUP(C159,Customers!A:E,5,FALSE) -> Mass Market | E159: PROD-0013 | F159: =VLOOKUP(Table1[[#This Row],[Product_ID]],Products!A:D,4,FALSE) -> Smartphones | G159: =VLOOKUP(H159,Stores!A:E,5,FALSE) -> Europe | H159: ST-011 | I159: Physical Store | J159: 3 | K159: 241.53 | L159: 0 | M159: Transfer | N159: 159.36 | O159: =Table1[[#This Row],[Unit_Price]]*Table1[[#This Row],[Quantity]] -> 724.59 | P159: =Table1[[#This Row],[Revenue]]-Table1[[#This Row],[COGS]] -> 246.51 | Q159: =Table1[[#This Row],[Profit]]/Table1[[#This Row],[Revenue]] -> 0.34020619 | R159: =Table1[[#This Row],[Cost Price]]*Table1[[#This Row],[Quantity]] -> 478.08
A160: ORD-10160 | B160: 45922 | C160: CUST-00352 | D160: =VLOOKUP(C160,Customers!A:E,5,FALSE) -> Premium | E160: PROD-0046 | F160: =VLOOKUP(Table1[[#This Row],[Product_ID]],Products!A:D,4,FALSE) -> Audio | G160: =VLOOKUP(H160,Stores!A:E,5,FALSE) -> Africa | H160: ST-003 | I160: Online | J160: 1 | K160: 79 | L160: 0.2 | M160: Transfer | N160: 57.67 | O160: =Table1[[#This Row],[Unit_Price]]*Table1[[#This Row],[Quantity]] -> 79 | P160: =Table1[[#This Row],[Revenue]]-Table1[[#This Row],[COGS]] -> 21.33 | Q160: =Table1[[#This Row],[Profit]]/Table1[[#This Row],[Revenue]] -> 0.27 | R160: =Table1[[#This Row],[Cost Price]]*Table1[[#This Row],[Quantity]] -> 57.67
A161: ORD-10161 | B161: 46138 | C161: CUST-00536 | D161: =VLOOKUP(C161,Customers!A:E,5,FALSE) -> Affluent | E161: PROD-0040 | F161: =VLOOKUP(Table1[[#This Row],[Product_ID]],Products!A:D,4,FALSE) -> Audio | G161: =VLOOKUP(H161,Stores!A:E,5,FALSE) -> Africa | H161: ST-006 | I161: Physical Store | J161: 2 | K161: 96.03 | L161: 0.05 | M161: Transfer | N161: 71.28 | O161: =Table1[[#This Row],[Unit_Price]]*Table1[[#This Row],[Quantity]] -> 192.06 | P161: =Table1[[#This Row],[Revenue]]-Table1[[#This Row],[COGS]] -> 49.5 | Q161: =Table1[[#This Row],[Profit]]/Table1[[#This Row],[Revenue]] -> 0.25773196 | R161: =Table1[[#This Row],[Cost Price]]*Table1[[#This Row],[Quantity]] -> 142.56
... A207: ORD-10208 | B207: 46100 | C207: CUST-00478 | D207: =VLOOKUP(C207,Customers!A:E,5,FALSE) -> Premium | E207: PROD-0044 | F207: =VLOOKUP(Table1[[#This Row],[Product_ID]],Products!A:D,4,FALSE) -> Audio | G207: =VLOOKUP(H207,Stores!A:E,5,FALSE) -> South America | H207: ST-017 | I207: Physical Store | J207: 1 | K207: 508.98 | L207: 0 | M207: Cash | N207: 354.29 | O207: =Table1[[#This Row],[Unit_Price]]*Table1[[#This Row],[Quantity]] -> 508.98 | P207: =Table1[[#This Row],[Revenue]]-Table1[[#This Row],[COGS]] -> 154.69 | Q207: =Table1[[#This Row],[Profit]]/Table1[[#This Row],[Revenue]] -> 0.30392157 | R207: =Table1[[#This Row],[Cost Price]]*Table1[[#This Row],[Quantity]] -> 354.29
A208: ORD-10209 | B208: 46298 | C208: CUST-00515 | D208: =VLOOKUP(C208,Customers!A:E,5,FALSE) -> Affluent | E208: PROD-0059 | F208: =VLOOKUP(Table1[[#This Row],[Product_ID]],Products!A:D,4,FALSE) -> #N/A | G208: =VLOOKUP(H208,Stores!A:E,5,FALSE) -> Africa | H208: ST-002 | I208: Online | J208: 3 | K208: 149 | L208: 0.05 | M208: Cash | N208: 0 | O208: 0 | P208: =Table1[[#This Row],[Revenue]]-Table1[[#This Row],[COGS]] -> 0 | Q208: 0 | R208: =Table1[[#This Row],[Cost Price]]*Table1[[#This Row],[Quantity]] -> 0
A209: ORD-10210 | B209: 45952 | C209: CUST-00331 | D209: =VLOOKUP(C209,Customers!A:E,5,FALSE) -> Premium | E209: PROD-0060 | F209: =VLOOKUP(Table1[[#This Row],[Product_ID]],Products!A:D,4,FALSE) -> Accessories | G209: =VLOOKUP(H209,Stores!A:E,5,FALSE) -> Asia | H209: ST-008 | I209: Physical Store | J209: 6 | K209: 106.82 | L209: 0.05 | M209: Card | N209: 78.48 | O209: =Table1[[#This Row],[Unit_Price]]*Table1[[#This Row],[Quantity]] -> 640.92 | P209: =Table1[[#This Row],[Revenue]]-Table1[[#This Row],[COGS]] -> 170.04 | Q209: =Table1[[#This Row],[Profit]]/Table1[[#This Row],[Revenue]] -> 0.26530612 | R209: =Table1[[#This Row],[Cost Price]]*Table1[[#This Row],[Quantity]] -> 470.88
A210: ORD-10211 | B210: 45850 | C210: CUST-00202 | D210: =VLOOKUP(C210,Customers!A:E,5,FALSE) -> Affluent | E210: PROD-0041 | F210: =VLOOKUP(Table1[[#This Row],[Product_ID]],Products!A:D,4,FALSE) -> Audio | G210: =VLOOKUP(H210,Stores!A:E,5,FALSE) -> South America | H210: ST-018 | I210: Physical Store | J210: 1 | K210: 175.42 | L210: 0.05 | M210: Transfer | N210: 110.98 | O210: =Table1[[#This Row],[Unit_Price]]*Table1[[#This Row],[Quantity]] -> 175.42 | P210: =Table1[[#This Row],[Revenue]]-Table1[[#This Row],[COGS]] -> 64.44 | Q210: =Table1[[#This Row],[Profit]]/Table1[[#This Row],[Revenue]] -> 0.36734694 | R210: =Table1[[#This Row],[Cost Price]]*Table1[[#This Row],[Quantity]] -> 110.98
A211: ORD-10212 | B211: 46027 | C211: CUST-00096 | D211: =VLOOKUP(C211,Customers!A:E,5,FALSE) -> MASS MARKET | E211: PROD-0033 | F211: =VLOOKUP(Table1[[#This Row],[Product_ID]],Products!A:D,4,FALSE) -> Laptops | G211: =VLOOKUP(H211,Stores!A:E,5,FALSE) -> Africa | H211: ST-006 | I211: Online | J211: 1 | K211: 2424.03 | L211: 0.1 | M211: Transfer | N211: 1599.36 | O211: =Table1[[#This Row],[Unit_Price]]*Table1[[#This Row],[Quantity]] -> 2424.03 | P211: =Table1[[#This Row],[Revenue]]-Table1[[#This Row],[COGS]] -> 824.67 | Q211: =Table1[[#This Row],[Profit]]/Table1[[#This Row],[Revenue]] -> 0.34020619 | R211: =Table1[[#This Row],[Cost Price]]*Table1[[#This Row],[Quantity]] -> 1599.36
A212: ORD-10213 | B212: 45891 | C212: CUST-00030 | D212: =VLOOKUP(C212,Customers!A:E,5,FALSE) -> Mass Market | E212: PROD-0006 | F212: =VLOOKUP(Table1[[#This Row],[Product_ID]],Products!A:D,4,FALSE) -> Televisions | G212: =VLOOKUP(H212,Stores!A:E,5,FALSE) -> Africa | H212: ST-002 | I212: Physical Store | J212: 3 | K212: 1286.01 | L212: 0.15 | M212: Transfer | N212: 948.27 | O212: =Table1[[#This Row],[Unit_Price]]*Table1[[#This Row],[Quantity]] -> 3858.03 | P212: =Table1[[#This Row],[Revenue]]-Table1[[#This Row],[COGS]] -> 1013.22 | Q212: =Table1[[#This Row],[Profit]]/Table1[[#This Row],[Revenue]] -> 0.26262626 | R212: =Table1[[#This Row],[Cost Price]]*Table1[[#This Row],[Quantity]] -> 2844.81
A213: ORD-10214 | B213: 46197 | C213: CUST-00032 | D213: =VLOOKUP(C213,Customers!A:E,5,FALSE) -> Mass Affluent | E213: PROD-0032 | F213: =VLOOKUP(Table1[[#This Row],[Product_ID]],Products!A:D,4,FALSE) -> Laptops | G213: =VLOOKUP(H213,Stores!A:E,5,FALSE) -> South America | H213: ST-018 | I213: Physical Store | J213: 3 | K213: 2220.99 | L213: 0 | M213: Transfer | N213: 1495.32 | O213: =Table1[[#This Row],[Unit_Price]]*Table1[[#This Row],[Quantity]] -> 6662.97 | P213: =Table1[[#This Row],[Revenue]]-Table1[[#This Row],[COGS]] -> 2177.01 | Q213: =Table1[[#This Row],[Profit]]/Table1[[#This Row],[Revenue]] -> 0.32673267 | R213: =Table1[[#This Row],[Cost Price]]*Table1[[#This Row],[Quantity]] -> 4485.96
A214: ORD-10215 | B214: 45759 | C214: CUST-00702 | D214: =VLOOKUP(C214,Customers!A:E,5,FALSE) -> Affluent | E214: PROD-0026 | F214: =VLOOKUP(Table1[[#This Row],[Product_ID]],Products!A:D,4,FALSE) -> Laptops | G214: =VLOOKUP(H214,Stores!A:E,5,FALSE) -> Asia | H214: ST-010 | I214: Physical Store | J214: 1 | K214: 1648.03 | L214: 0 | M214: Cash | N214: 1240.27 | O214: =Table1[[#This Row],[Unit_Price]]*Table1[[#This Row],[Quantity]] -> 1648.03 | P214: =Table1[[#This Row],[Revenue]]-Table1[[#This Row],[COGS]] -> 407.76 | Q214: =Table1[[#This Row],[Profit]]/Table1[[#This Row],[Revenue]] -> 0.24742268 | R214: =Table1[[#This Row],[Cost Price]]*Table1[[#This Row],[Quantity]] -> 1240.27
A215: ORD-10216 | B215: 46095 | C215: CUST-00426 | D215: =VLOOKUP(C215,Customers!A:E,5,FALSE) -> Mass Market | E215: PROD-0031 | F215: =VLOOKUP(Table1[[#This Row],[Product_ID]],Products!A:D,4,FALSE) -> Laptops | G215: =VLOOKUP(H215,Stores!A:E,5,FALSE) -> North America | H215: ST-015 | I215: Online | J215: 2 | K215: 1630.98 | L215: 0 | M215: Transfer | N215: 991.38 | O215: =Table1[[#This Row],[Unit_Price]]*Table1[[#This Row],[Quantity]] -> 3261.96 | P215: =Table1[[#This Row],[Revenue]]-Table1[[#This Row],[COGS]] -> 1279.2 | Q215: =Table1[[#This Row],[Profit]]/Table1[[#This Row],[Revenue]] -> 0.39215686 | R215: =Table1[[#This Row],[Cost Price]]*Table1[[#This Row],[Quantity]] -> 1982.76
A216: ORD-10217 | B216: 46327 | C216: CUST-00752 | D216: =VLOOKUP(C216,Customers!A:E,5,FALSE) -> Mass Affluent | E216: PROD-0056 | F216: =VLOOKUP(Table1[[#This Row],[Product_ID]],Products!A:D,4,FALSE) -> Accessories | G216: =VLOOKUP(H216,Stores!A:E,5,FALSE) -> Europe | H216: ST-012 | I216: Physical Store | J216: 1 | K216: 154.23 | L216: 0.1 | M216: Transfer | N216: 116.07 | O216: =Table1[[#This Row],[Unit_Price]]*Table1[[#This Row],[Quantity]] -> 154.23 | P216: =Table1[[#This Row],[Revenue]]-Table1[[#This Row],[COGS]] -> 38.16 | Q216: =Table1[[#This Row],[Profit]]/Table1[[#This Row],[Revenue]] -> 0.24742268 | R216: =Table1[[#This Row],[Cost Price]]*Table1[[#This Row],[Quantity]] -> 116.07
A217: ORD-10218 | B217: 46157 | C217: CUST-00109 | D217: =VLOOKUP(C217,Customers!A:E,5,FALSE) -> Mass Market | E217: PROD-0021 | F217: =VLOOKUP(Table1[[#This Row],[Product_ID]],Products!A:D,4,FALSE) -> Smartphones | G217: =VLOOKUP(H217,Stores!A:E,5,FALSE) -> Asia | H217: ST-008 | I217: Physical Store | J217: 1 | K217: 453.49 | L217: 0.2 | M217: Cash | N217: 278.38 | O217: =Table1[[#This Row],[Unit_Price]]*Table1[[#This Row],[Quantity]] -> 453.49 | P217: =Table1[[#This Row],[Revenue]]-Table1[[#This Row],[COGS]] -> 175.11 | Q217: =Table1[[#This Row],[Profit]]/Table1[[#This Row],[Revenue]] -> 0.38613861 | R217: =Table1[[#This Row],[Cost Price]]*Table1[[#This Row],[Quantity]] -> 278.38
...

Sheet Customers
A1: Customer_ID | B1: Customer_Name | C1: Gender | D1: Age | E1: Customer_Segment | F1: Country | G1: Region | H1: Registration_Date
A2: CUST-00001 | B2: Linh Ndlovu | C2: Female | D2: 57 | E2: Mass Market | F2: Brazil | G2: South America | H2: 45765
A3: CUST-00002 | B3: Sophia Bello | C3: Male | D3: 25 | E3: Mass Affluent | F3: Morocco | G3: Africa | H3: 29/01/2026
A4: CUST-00003 | B4: Zoe Garcia | C4: Female | D4: 0 | E4: Mass Market | F4: India | G4: Asia | H4: 46097
A5: CUST-00004 | B5: Sofia Jones | C5: Male | D5: 30 | E5: MASS MARKET | F5: Ghana | G5: Africa | H5: 45552
A6: CUST-00005 | B6: Hannah Kumar | C6: Female | D6: 45 | E6: Mass Affluent | F6: Japan | G6: Asia | H6: 2023/09/15
A7: CUST-00006 | B7: Sofia Mensah | C7: Female | D7: 23 | E7: Mass Market | F7: Philippines | G7: Asia | H7: 45972
A8: CUST-00007 | B8: Ada Dlamini | C8: Male | D8: 53 | E8: Mass Affluent | F8: Kenya | G8: Africa | H8: 45669
A9: CUST-00008 | B9: Evelyn Kumar | C9: Male | D9: 72 | E9: Premium | F9: Philippines | G9: Asia | H9: 46054
A10: CUST-00009 | B10: Ada Suzuki | C10: Female | D10: 46 | E10: Mass Affluent | F10: Malaysia | G10: Asia | H10: 45503
A11: CUST-00010 | B11: Tunde Wang | C11: Female | D11: 28 | E11: Affluent | F11: Colombia | G11: South America | H11: 46123
A12: CUST-00011 | B12: Linh Okafor | C12: Male | D12: 66 | E12: Mass Affluent | F12: South Africa | G12: Africa | H12: 45837
A13: CUST-00012 | B13: Jason Singh | C13: Female | D13: 36 | E13: Mass Affluent | F13: Australia | G13: Oceania | H13: 45865
A14: CUST-00013 | B14: Ifeoma Haddad | C14: Male | D14: 58 | E14: Mass Market | F14: Nigeria | G14: Africa | H14: 46182
A15: CUST-00014 | B15: Charles Adeyemi | C15: Male | D15: 27 | E15: Premium | F15: Brazil | G15: South America | H15: 45663
A16: CUST-00015 | B16: Anthony Walker | C16: Female | D16: 24 | E16: Mass Market | F16: Kenya | G16: africa | H16: 45444
A17: CUST-00016 | B17: Sofia Chen | C17: Male | D17: 71 | E17: Mass Market | F17: Brazil | G17: South America | H17: 45639
A18: CUST-00017 | B18: Isabella Santos | C18: Female | D18: 70 | E18: Affluent | F18: India | G18: Asia | H18: 46064
... A26: CUST-00025 | B26: Mei Garcia | C26: Female | D26: 51 | E26: Mass Affluent | F26: South Africa | G26: Africa | H26: 46118
A27: CUST-00026 | B27: Sophia Costa | C27: Male | D27: 38 | E27: Mass Market | F27: Australia | G27: Oceania
A28: CUST-00027 | B28: Thomas Davis | C28: Female | D28: 60 | E28: Mass Market | F28: Malaysia | G28: Asia | H28: 46202
A29: CUST-00028 | B29: Aisha Park | C29: Female | D29: 26 | E29: Mass Market | F29: Singapore | G29: Asia | H29: 45360
A30: CUST-00029 | B30: Lily Lim | C30: Female | D30: 68 | E30: Mass Market | F30: China | G30: Asia | H30: 45778
A31: CUST-00030 | B31: Eric Tran | C31: Female | D31: 48 | E31: Mass Market | F31: United States | G31: North America | H31: 45386
A32: CUST-00031 | B32: Sofia Sharma | C32: Female | D32: 53 | E32: Mass Market | F32: Nigeria | G32: Africa | H32: 46200
A33: CUST-00032 | B33: Nur Adeyemi | C33: Female | D33: 55 | E33: Mass Affluent | F33: Italy | G33: Europe | H33: 45783
A34: CUST-00033 | B34: Linh Anderson | C34: Male | D34: 64 | E34: Mass Market | F34: Ghana | G34: Africa | H34: 45005
A35: CUST-00034 | B35: Grace White | C35: Female | D35: 20 | E35: Premium | F35: South Africa | G35: Africa | H35: 45214
A36: CUST-00035 | B36: Aria Brown | C36: Male | D36: 22 | E36: Mass Affluent | F36: United Kingdom | G36: Europe | H36: 46118
A37: CUST-00036 | B37: Brian Walker | C37: Female | D37: 41 | E37: Mass Market | F37: Mexico | G37: North America | H37: 45127
A38: CUST-00037 | B38: Emma Okafor | C38: Female | D38: 19 | E38: Affluent | F38: Chile | G38: South America | H38: 05/03/2024
A39: CUST-00038 | B39: Harper Sato | D39: 52 | E39: Mass Market | F39: Egypt | G39: Africa | H39: 45930
A40: CUST-00039 | B40: John Williams | C40: Male | D40: 59 | E40: Mass Market | F40: Colombia | G40: South America | H40: 10/08/2025
A41: CUST-00040 | B41: David Singh | C41: Female | D41: 47 | E41: Mass Market | F41: Morocco | G41: Africa | H41: 46157
A42: CUST-00041 | B42: Charlotte Sato | C42: Female | D42: 34 | E42: Mass Market | F42: Kenya | G42: Africa | H42: 45848
A43: CUST-00042 | B43: Amelia Miller | C43: Female | D43: 69 | E43: Mass Market | G43: North America | H43: 45904
A44: CUST-00043 | B44: Sofia Hassan | C44: MALE | D44: 51 | E44: Mass Market | F44: Mexico | G44: North America | H44: 46068
A45: CUST-00044 | B45: Ngozi Sharma | C45: Female | D45: 72 | E45: Mass Market | F45: Spain | G45: Europe | H45: 45190
A46: CUST-00045 | B46: Sophia Moore | C46: Male | D46: 46 | E46: Mass Affluent | F46: Chile | G46: South America | H46: 45848
A47: CUST-00046 | B47: Fatima Wilson | C47: Female | D47: 26 | E47: VIP | F47: Netherlands | G47: Europe | H47: 46201
A48: CUST-00047 | B48: Ravi Costa | C48: Male | D48: 15 | E48: Affluent | F48: Netherlands | G48: Europe | H48: 44990
A49: CUST-00048 | B49: Fatima Mensah | C49: Male | D49: 52 | E49: Mass Market | F49: Morocco | G49: Africa | H49: 46070
A50: CUST-00049 | B50: Tunde Sharma | C50: Male | D50: 26 | E50: Mass Market | F50: Italy | G50: Europe | H50: 46095
A51: CUST-00050 | B51: Michael Lim | C51: Male | D51: 21 | E51: Mass Market | F51: Spain | G51: Europe | H51: 45330
A52: CUST-00051 | B52: Carlos Jackson | C52: Male | D52: 23 | E52: Premium | F52: Ghana | G52: Africa | H52: 45469
A53: CUST-00052 | B53: Harper Sharma | C53: Female | D53: 69 | E53: Mass Affluent | F53: Philippines | G53: Asia | H53: 45041
A54: CUST-00053 | B54: Jason Mensah | C54: Female | D54: 45 | E54: Mass Market | F54: Malaysia | G54: Asia | H54: 46208
A55: CUST-00054 | B55: Emma Sato | C55: Female | D55: 72 | E55: Mass Market | F55: Malaysia | G55: Asia | H55: 45823
... A69: CUST-00068 | B69: Thuy Brown | C69: Female | D69: 70 | E69: Mass Affluent | F69: United Kingdom | G69: Europe | H69: 45944
A70: CUST-00069 | B70: Robert Harris | C70: Male | D70: 29 | E70: Affluent | F70: Kenya | H70: 46175
A71: CUST-00070 | B71: Aisha Singh | C71: Male | D71: 68 | E71: Affluent | F71: South Africa | G71: Africa | H71: 46036
A72: CUST-00071 | B72: Mei Ali | C72: Female | E72: Mass Affluent | F72: Ghana | G72: Africa | H72: 45625
A73: CUST-00072 | B73: Ngozi Harris | C73: Male | D73: 27 | E73: Mass Market | F73: New Zealand | G73: Oceania | H73: 45352
A74: CUST-00073 | B74: Daniel Smith | C74: Female | D74: 48 | E74: Mass Market | F74: Malaysia | G74: Asia | H74: 46041
A75: CUST-00074 | B75: Priya Haddad | C75: Female | D75: 41 | E75: mass market | F75: Netherlands | G75: Europe | H75: 45670
A76: CUST-00075 | B76: Sofia Brown | C76: Male | D76: 37 | E76: Mass Market | F76: Kenya | G76: Africa | H76: 45389
A77: CUST-00076 | B77: Sophia Jackson | C77: Male | D77: 63 | E77: mass market | F77: Australia | G77: Oceania | H77: 46131
A78: CUST-00077 | B78: Min Sato | C78: Female | D78: 23 | E78: Mass Market | F78: Egypt | G78: Africa | H78: 45032
A79: CUST-00078 | B79: Zoe Clark | C79: Female | D79: 69 | E79: Mass Market | F79: South Africa | G79: Africa | H79: 16-01-2025
A80: CUST-00079 | B80: Ananya White | C80: Female | D80: 61 | E80: Mass Affluent | F80: China | G80: Asia | H80: 45167
A81: CUST-00080 | B81: Siti Martinez | C81: Male | D81: 18 | E81: Mass Market | F81: Morocco | G81: AFRICA | H81: 45250
A82: CUST-00081 | B82: Mia Miller | C82: Female | D82: 69 | E82: Affluent | F82: Morocco | G82: Africa | H82: 46044
A83: CUST-00082 | B83: Isabella Garcia | D83: 49 | E83: Mass Market | F83: Spain | G83: Europe | H83: 45896
A84: CUST-00083 | B84: Christopher Walker | C84: Female | E84: Affluent | F84: France | G84: Europe | H84: 45210
A85: CUST-00084 | B85: Ada Walker | C85: Male | D85: 39 | E85: Mass Market | F85: United Kingdom | G85: Europe | H85: 45237
A86: CUST-00085 | B86: Min Wang | C86: Male | D86: 47 | E86: Affluent | F86: Colombia | G86: South America | H86: 45003
A87: CUST-00086 | B87: Hana Zhang | C87: Female | D87: 61 | E87: Mass Market | F87: Malaysia | G87: Asia | H87: 46053
A88: CUST-00087 | B88: Aria Okoro | C88: Female | D88: 62 | E88: Premium | F88: China | G88: Asia | H88: 46066
A89: CUST-00088 | B89: Carlos Nguyen | C89: Male | D89: 40 | E89: Mass Affluent | F89: Australia | G89: Oceania | H89: 45083
A90: CUST-00089 | B90: Amelia Rahman | C90: Male | D90: 21 | E90: VIP | F90: Kenya | G90: Africa | H90: 45295
A91: CUST-00090 | B91: Joseph Wilson | C91: Female | D91: 71 | E91: Affluent | F91: Italy | G91: Europe | H91: 45377
A92: CUST-00091 | B92: Ella Singh | C92: Male | D92: 45 | E92: Mass Affluent | F92: Italy | G92: Europe | H92: 45618
A93: CUST-00092 | C93: Female | D93: 33 | E93: Mass Market | F93: Italy | G93: Europe | H93: 45123
A94: CUST-00093 | B94: Yuki Martin | C94: Male | D94: 41 | E94: Mass Affluent | F94: Nigeria | G94: Africa | H94: 17/01/2025
A95: CUST-00094 | B95: Brian Mensah | C95: Female | D95: 52 | E95: Mass Market | F95: South Africa | G95: Africa | H95: 45619
A96: CUST-00095 | B96: Ryan Singh | C96: Female | D96: 50 | E96: Mass Affluent | F96: Brazil | G96: South America | H96: 44992
A97: CUST-00096 | B97: Andrew Mensah | C97: Male | D97: 25 | E97: MASS MARKET | F97: United Kingdom | G97: Europe | H97: 45426
A98: CUST-00097 | B98: Ava Suzuki | C98: Female | D98: 62 | E98: Mass Market | F98: India | G98: Asia | H98: 46188
A99: CUST-00098 | B99: John Taylor | C99: Male | D99: 26 | E99: Mass Market | F99: China | G99: Asia | H99: 45627
A100: CUST-00099 | B100: Daniel Thompson | C100: Male | E100: Mass Affluent | F100: United States | G100: North America | H100: 44992
A101: CUST-00100 | B101: Kevin Morris | C101: Male | D101: 61 | E101: Mass Market | F101: Germany | G101: Europe | H101: 46108
A102: CUST-00101 | B102: Ava Kumar | C102: Female | D102: 44 | E102: Premium | F102: Colombia | G102: South America | H102: 45224
A103: CUST-00102 | B103: Priya Williams | C103: Female | D103: 69 | E103: Mass Market | F103: New Zealand | G103: Oceania | H103: 45465
A104: CUST-00103 | B104: Carlos Smith | C104: Male | D104: 34 | E104: Mass Affluent | F104: Colombia | G104: South America | H104: 45204
A105: CUST-00104 | B105: Maya Bello | C105: Male | D105: 18 | E105: Mass Affluent | F105: South Africa | G105: Africa | H105: 45101
A106: CUST-00105 | B106: Chinedu Robinson | C106: Male | D106: 60 | E106: Mass Market | F106: Singapore | G106: Asia | H106: 46123
A107: CUST-00106 | B107: Ryan Lim | C107: Male | D107: 68 | E107: Premium | F107: Ghana | G107: Africa | H107: 46163
A108: CUST-00107 | B108: Thuy Okoro | C108: Female | D108: 20 | E108: Mass Market | F108: Canada | G108: North America | H108: 45756
A109: CUST-00108 | B109: Lucia Williams | C109: Male | D109: 18 | E109: Mass Affluent | F109: India | G109: Asia | H109: 44975
A110: CUST-00109 | B110: Chloe Ibrahim | C110: Female | D110: 41 | E110: Mass Market | F110: Mexico | G110: North America | H110: 46115
A111: CUST-00110 | B111: Chioma Ali | C111: Female | D111: 23 | E111: Affluent | F111: Japan | G111: Asia | H111: 45367
A112: CUST-00111 | B112: Wei Bello | C112: Female | D112: 51 | E112: Mass Market | F112: India | G112: Asia | H112: 45201
... A118: CUST-00117 | B118: Tunde Dlamini | C118: Male | D118: 60 | E118: Mass Affluent | F118: Canada | G118: NORTH AMERICA | H118: 45761
A119: CUST-00118 | B119: Chloe Garcia | C119: Male | D119: 36 | F119: Spain | G119: Europe | H119: 45154
A120: CUST-00119 | B120: David White | C120: Male | D120: 43 | E120: Affluent | F120: Ghana | G120: Africa | H120: 45528
A121: CUST-00120 | B121: Joseph Suzuki | C121: Male | D121: 67 | E121: Mass Market | F121: Morocco | G121: AFRICA | H121: 45371
A122: CUST-00121 | B122: Sofia Taylor | C122: FEMALE | D122: 61 | E122: Mass Market | F122: Nigeria | G122: Africa | H122: 45677
A123: CUST-00122 | B123: Ella Mwangi | C123: Male | D123: 43 | E123: VIP | F123: France | G123: Europe | H123: 45941
A124: CUST-00123 | B124: William Thomas | C124: Male | D124: 28 | E124: Mass Affluent | F124: United Kingdom | G124: Europe | H124: 45369
A125: CUST-00124 | B125: Amara Tan | C125: Female | D125: 65 | E125: Premium | F125: Nigeria | G125: Africa | H125: 45682
...

Sheet Products
A1: Product_ID | B1: Product_Name | C1: Category | D1: Sub_Category | E1: Cost_Price | F1: Supplier
A2: PROD-0001 | B2: Smart LED TV | C2: Electronics | D2: Televisions | E2: 433.38 | F2: Vertex Supply Co.
A3: PROD-0002 | B3: Smart LED TV Pro | C3: Electronics | D3: Televisions | E3: 679.32 | F3: GlobalTech Supply
A4: PROD-0003 | B4: 4K Smart TV | C4: Electronics | D4: Televisions | E4: 767.36 | F4: Nova Electronics
A5: PROD-0004 | B5: 4K Smart TV Pro | C5: Electronics | D5: Televisions | E5: 1064.29 | F5: Pacific Traders
A6: PROD-0005 | B6: 4K Smart TV Pro | C6: Electronics | D6: Televisions | E6: 989.34 | F6: BlueWave Imports
A7: PROD-0006 | B7: QLED TV | C7: Electronics | D7: Televisions | E7: 948.27 | F7: Prime Distribution
A8: PROD-0007 | B8: OLED TV | C8: Electronics | D8: Televisions | E8: 1097.39 | F8: EastWest Distribution
A9: PROD-0008 | B9: OLED TV Pro | C9: Electronics | D9: Televisions | E9: 1586.31 | F9: Metro Wholesale
A10: PROD-0009 | B10: OLED TV Plus | C10: Electronics | D10: Televisions | E10: 1299.35 | F10: Apex Goods
A11: PROD-0010 | B11: QLED TV | C11: Electronics | D11: Televisions | E11: 1007.28 | F11: Horizon Supplies
A12: PROD-0011 | B12: QLED TV Pro | C12: Electronics | D12: Televisions | E12: 1177.38 | F12: Vertex Supply Co.
A13: PROD-0012 | B13: QLED TV Plus | C13: Electronics | D13: Televisions | E13: 1427.32 | F13: GlobalTech Supply
... A61: PROD-0060 | B61: Webcam Plus | C61: Electronics | D61: Accessories | E61: 78.48 | F61: Horizon Supplies

Sheet Stores
A1: Store_ID | B1: Store_Name | C1: City | D1: Country | E1: Region | F1: Store_Type | G1: Manager
A2: ST-001 | B2: NovaMart Lagos Central | C2: Lagos | D2: NIGERIA | E2: Africa | F2: Flagship | G2: Amara Okafor
A3: ST-002 | B3: NovaMart Abuja City | C3: Abuja | D3: Nigeria | E3: Africa | F3: Standard | G3: Daniel Bello
A4: ST-003 | B4: NovaMart Johannesburg | C4: Johannesburg | D4: south africa | E4: Africa | F4: Flagship | G4: Thabo Mokoena
A5: ST-004 | B5: NovaMart Cape Town | C5: Cape Town | D5: South Africa | E5: Africa | F5: Standard | G5: Lerato Dlamini
A6: ST-005 | B6: NovaMart Nairobi | C6: Nairobi | D6: Kenya | E6: Africa | F6: standard | G6: Brian Mwangi
A7: ST-006 | B7: NovaMart Accra | C7: Accra | D7: Ghana | E7: Africa | F7: Outlet | G7: Kwame Mensah
A8: ST-007 | B8: NovaMart Mumbai | C8: Mumbai | D8: India | E8: Asia | F8: Flagship | G8: Priya Sharma
A9: ST-008 | B9: NovaMart Singapore Central | C9: singapore | D9: Singapore | E9: Asia | F9: Flagship | G9: Daniel Tan
A10: ST-009 | B10: NovaMart Tokyo | C10: tokyo | D10: Japan | E10: Asia | F10: Standard | G10: Yuki Sato
A11: ST-010 | B11: NovaMart Kuala Lumpur | C11: Kuala Lumpur | D11: Malaysia | E11: Asia | F11: Standard | G11: Nur Rahman
A12: ST-011 | B12: NovaMart London | C12: London | D12: United Kingdom | E12: Europe | F12: FLAGSHIP | G12: Emma Williams
... A14: ST-013 | B14: NovaMart Paris | C14: Paris | D14: France | E14: EUROPE | F14: Standard | G14: Claire Martin
A15: ST-014 | B15: NovaMart New York | C15: New York | D15: United States | E15: North America | F15: Flagship
A16: ST-015 | B16: NovaMart Toronto | C16: Toronto | D16: Canada | E16: North America | F16: Standard | G16: Olivia Brown
A17: ST-016 | B17: NovaMart Mexico City | C17: Mexico City | D17: Mexico | E17: North America | F17: Outlet
A18: ST-017 | B18: NovaMart São Paulo | C18: São Paulo | D18: Brazil | E18: South America | F18: Flagship | G18: Lucas Silva
A19: ST-018 | B19: NovaMart Buenos Aires | C19: Buenos Aires | D19: Argentina | E19: South America | F19: standard | G19: Sofia Martinez
A20: ST-019 | B20: NovaMart Sydney | C20: Sydney | D20: Australia | E20: Oceania | F20: Flagship | G20: Jack Taylor
A21: ST-020 | B21: NovaMart Auckland | C21: Auckland | D21: New Zealand | E21: oceania | F21: Standard | G21: Mia Wilson

Sheet Pivot Tables
A2: Total Sale and Profit | F2: Monthly sales trend | O2: Product by revenue and Profit | AB2: Region by Revenue and Profit | BD2: Customer Segement by Revenue and Profit
A3: Revenue | B3: Average of Profit Margin | C3: Sum of Profit | D3: Sum of COGS | AQ3: Row Labels | AR3: Revenue
A4: 7163748.5 | B4: 0.32300081 | C4: 2357640.1 | D4: 4806108.4 | F4: Row Labels | G4: Revenue | O4: Products | P4: P-Revenue | Q4: P-Profit | R4: P-Unit_Price | AQ4: ST-013 | AR4: 436414.83 | BR4: Top 5 Customers by Revenue | CF4: Online Perfomance Compare with Physical Store | CQ4: Profitability
A5: =GETPIVOTDATA(" Revenue",$A$3) -> 7163748.5 | C5: =GETPIVOTDATA("Sum of Profit",$A$3) -> 2357640.1 | D5: =GETPIVOTDATA("Sum of COGS",$A$3) -> 4806108.4 | F5: Jan | G5: 559225.96 | O5: PROD-0033 | P5: 380022.93 | Q5: 136920.21 | R5: 132471.99 | AC5: Regions | AD5: Revenue | AE5: R-Profit | AQ5: ST-004 | AR5: 401065.27 | BD5: Customer Segement | BE5: Revenue | BF5: Profit. | BR5: Row Labels | BS5: Revenue | CE5: .Profit | CF5: Column Labels | CI5: Sum of Revenue | CJ5: Column Labels | CQ5: Sum of Profit Margin | CR5: Column Labels
F6: Feb | G6: 500115.59 | O6: PROD-0009 | P6: 327995.92 | Q6: 114902.52 | R6: 118040.95 | AC6: Africa | AD6: 2230807.5 | AE6: 736587.24 | AQ6: ST-005 | AR6: 395098.03 | BD6: Affluent | BE6: 71701.84 | BF6: 23172.96 | BR6: CUST-00257 | BS6: 41708.01 | CE6: Channel | CF6: Online Store | CG6: Physical Store | CH6: Grand Total | CI6: Channel | CJ6: Online Store | CK6: Physical Store | CL6: Grand Total | CQ6: Row Labels | CR6: Accessories | CS6: Audio | CT6: Laptops | CU6: Smartphones | CV6: Televisions | CW6: #N/A | CX6: Grand Total
F7: Mar | G7: 635411.58 | O7: PROD-0007 | P7: 300990.69 | Q7: 117726.56 | R7: 104324.01 | AC7: Asia | AD7: 1059389 | AE7: 348130.25 | AQ7: ST-018 | AR7: 387126.92 | BD7: PROD-0012 | BE7: 71701.84 | BF7: 23172.96 | BR7: CUST-00384 | BS7: 35114.94 | CE7: 2025 | CF7: 496671.29 | CG7: 479026.66 | CH7: 975697.95 | CI7: 2025 | CJ7: 1492943.6 | CK7: 1461372.1 | CL7: 2954315.6 | CQ7: PROD-0007 | CV7: 22.206967 | CX7: 22.206967
B8: Overall Profit Margin | F8: Apr | G8: 538607.8 | O8: PROD-0012 | P8: 294720.59 | Q8: 94895.79 | R8: 119978.84 | AC8: Asia | AD8: 339356.76 | AE8: 111046.17 | AQ8: ST-006 | AR8: 386093.1 | BD8: Mass Affluent | BE8: 112813.6 | BF8: 30955.78 | BR8: CUST-00395 | BS8: 39948.97 | CE8: 2026 | CF8: 680234.76 | CG8: 701707.38 | CH8: 1381942.1 | CI8: 2026 | CJ8: 2092514.1 | CK8: 2116918.8 | CL8: 4209432.9 | CQ8: PROD-0009 | CV8: 20.669738 | CX8: 20.669738
B9: =GETPIVOTDATA("Sum of Profit",$A$3)/GETPIVOTDATA(" Revenue",$A$3) -> 0.32910704 | F9: May | G9: 580586.48 | O9: PROD-0032 | P9: 294402.12 | Q9: 92533.92 | R9: 100340.37 | AC9: Europe | AD9: 1109903.4 | AE9: 365284.6 | AQ9: ST-020 | AR9: 376169.22 | BD9: PROD-0026 | BE9: 112813.6 | BF9: 30955.78 | BR9: CUST-00473 | BS9: 52971.45 | CE9: Grand Total | CF9: 1176906 | CG9: 1180734 | CH9: 2357640.1 | CI9: Grand Total | CJ9: 3585457.6 | CK9: 3578290.9 | CL9: 7163748.5 | CQ9: PROD-0013 | CU9: 20.79502 | CX9: 20.79502
F10: Jun | G10: 578475.62 | O10: Grand Total | P10: 1598132.3 | Q10: 556979 | R10: 575156.16 | AC10: North America | AD10: 982913.68 | AE10: 320921.51 | AQ10: ST-009 | AR10: 369470.91 | BD10: Mass Market | BE10: 167433 | BF10: 60275.88 | BR10: CUST-00661 | BS10: 35121.3 | CQ10: PROD-0027 | CT10: 20.960759 | CX10: 20.960759
A11: Count of Order_ID | F11: Jul | G11: 671517.29 | AC11: oceania | AD11: 701211.91 | AE11: 233168.26 | AQ11: ST-010 | AR11: 362401.03 | BD11: PROD-0033 | BE11: 167433 | BF11: 60275.88 | BR11: Grand Total | BS11: 204864.67 | CQ11: PROD-0051 | CR11: 22.450686 | CX11: 22.450686
A12: 2960 | F12: Aug | G12: 594498.2 | AC12: South America | AD12: 740166.29 | AE12: 242502.06 | AQ12: ST-001 | AR12: 359916.23 | BD12: Premium | BE12: 61659.18 | BF12: 18828.81 | CQ12: Grand Total | CR12: 22.450686 | CT12: 20.960759 | CU12: 20.79502 | CV12: 42.876705 | CX12: 107.08317
A13: =GETPIVOTDATA("Order_ID",$A$11) -> 2960 | F13: Sep | G13: 528323.22 | AC13: Grand Total | AD13: 7163748.5 | AE13: 2357640.1 | AQ13: ST-017 | AR13: 350158.96 | BD13: PROD-0008 | BE13: 61659.18 | BF13: 18828.81
F14: Oct | G14: 637179.38 | AQ14: ST-003 | AR14: 346794.06 | BD14: VIP | BE14: 28015.26 | BF14: 8576.1
F15: Nov | G15: 601250.87 | AQ15: ST-012 | AR15: 342961.2 | BD15: PROD-0032 | BE15: 28015.26 | BF15: 8576.1
B16: Avg Order Value | F16: Dec | G16: 738556.54 | AQ16: ST-015 | AR16: 342335.78 | BD16: Grand Total | BE16: 441622.88 | BF16: 141809.53
B17: =A5/A13 -> 2420.1853 | F17: Grand Total | G17: 7163748.5 | AQ17: ST-014 | AR17: 339818.2
B18: =B17 -> 2420.1853 | AQ18: ST-007 | AR18: 339356.76
AQ19: ST-002 | AR19: 332465.52
AQ20: ST-008 | AR20: 325960.03
AQ21: ST-019 | AR21: 325042.69
AQ22: ST-011 | AR22: 311484.71
F23: Row Labels | G23: Sum of Profit | O23: Products | P23: Sum of Revenue | Q23: Sum of Profit | AQ23: ST-016 | AR23: 292789.96
F24: Jan | G24: 188017.82 | O24: Affluent | P24: 1030894.4 | Q24: 340580.9 | AQ24: Grand Total | AR24: 7122923.4
F25: Feb | G25: 162502.11 | O25: Mass Affluent | P25: 1630124.3 | Q25: 535547.19
F26: Mar | G26: 206298.15 | O26: Mass Affluent | P26: 4561.68 | Q26: 1627.86
F27: Apr | G27: 176144.78 | O27: Mass Market | P27: 3283703.3 | Q27: 1076302.6
F28: May | G28: 187797.56 | O28: Mass Market | P28: 62011.4 | Q28: 21396.53
F29: Jun | G29: 187636.05 | O29: Premium | P29: 869494.97 | Q29: 291668.06
F30: Jul | G30: 223130.69 | O30: Premium | P30: 20380.46 | Q30: 7051.7
F31: Aug | G31: 194975.49 | O31: VIP | P31: 207193.72 | Q31: 65964.33
F32: Sep | G32: 173439.38 | O32: Grand Total | P32: 7108364.2 | Q32: 2340139.2
F33: Oct | G33: 212357.58
F34: Nov | G34: 201144.45
F35: Dec | G35: 244196.03
F36: Grand Total | G36: 2357640.1

Sheet new dashboard

Sheet new dashboard (2)

Sheet Recommendation
